Workbook

Sheet Tabla 1
A1: Fecha | B1: Título de la Nota | C1: Medio | D1: Gestión | E1: Detalle de Gestión | F1: Síntesis | G1: Link | H1: Tipo de Medio | I1: Tier | J1: Valor de Retorno ($$) | K1: Tono (K) | L1: Mensaje Clave (L) | M1: Eje/Tema (M) | N1: Subtema (N) | O1: Voceros (O) | P1: % del Tema (P)
A2: 46024 | B2: El complejo recreativo Maldonado reabre sus puertas para la temporada 2026 | C2: La Nueva Provincia | D2: Espontánea | E2: Orgánica | F2: Anuncio de la reapertura del complejo recreativo Maldonado para la temporada de verano 2026. | G2: https://www.lanueva.com/nota/2025-12-30-17-13-0-el-complejo-recreativo-maldonado-reabre-sus-puertas-para-la-temporada-2026 | H2: =IF(C2="", "", IFERROR(VLOOKUP(C2, 'Tabla 2'!$A$2:$D$298, 2, FALSE), "")) -> Local BB | I2: =IF(C2="", "", IFERROR(VLOOKUP(C2, 'Tabla 2'!$A$2:$D$298, 3, FALSE), "")) -> 1 | J2: =IF(C2="", "", IFERROR(VLOOKUP(C2, 'Tabla 2'!$A$2:$D$298, 4, FALSE), "")) -> 900000 | K2: Positivo | L2: TRUE | M2: Sustentabilidad | N2: Relaciones con la Comunidad | O2: No menciona | P2: 1
A3: 46024 | B3: El complejo recreativo Maldonado reabre sus puertas para la temporada 2026 | C3: Ingeniero White | D3: Espontánea | E3: Orgánica | F3: Noticia sobre la reapertura del complejo recreativo Maldonado para la temporada 2026. | G3: https://www.ingenierowhite.com/2025/12/30/el-complejo-recreativo-maldonado-reabre-sus-puertas-para-la-temporada-2026/ | H3: =IF(C3="", "", IFERROR(VLOOKUP(C3, 'Tabla 2'!$A$2:$D$298, 2, FALSE), "")) -> Local BB | I3: =IF(C3="", "", IFERROR(VLOOKUP(C3, 'Tabla 2'!$A$2:$D$298, 3, FALSE), "")) -> 1 | J3: =IF(C3="", "", IFERROR(VLOOKUP(C3, 'Tabla 2'!$A$2:$D$298, 4, FALSE), "")) -> 500000 | K3: Positivo | L3: TRUE | M3: Sustentabilidad | N3: Relaciones con la Comunidad | O3: No menciona | P3: 1
A4: 46024 | B4: El viernes abrirá sus puertas el balneario Maldonado | C4: Frente a Cano | D4: Espontánea | E4: Orgánica | F4: Anuncio de la apertura del balneario Maldonado el próximo viernes. | G4: https://frenteacano.com.ar/el-viernes-abrira-sus-puertas-el-balneario-maldonado/ | H4: =IF(C4="", "", IFERROR(VLOOKUP(C4, 'Tabla 2'!$A$2:$D$298, 2, FALSE), "")) -> Local BB | I4: =IF(C4="", "", IFERROR(VLOOKUP(C4, 'Tabla 2'!$A$2:$D$298, 3, FALSE), "")) -> 1 | J4: =IF(C4="", "", IFERROR(VLOOKUP(C4, 'Tabla 2'!$A$2:$D$298, 4, FALSE), "")) -> 800000 | K4: Positivo | L4: TRUE | M4: Sustentabilidad | N4: Relaciones con la Comunidad | O4: No menciona | P4: 1
A5: 46024 | B5: Complejo Maldonado abre sus puertas el viernes | C5: Canal 7 Bahia Blanca | D5: Espontánea | E5: Orgánica | F5: Detalles sobre la apertura del Complejo Maldonado, incluyendo horarios y normas de ingreso. | G5: https://www.canalsiete.com.ar/c7-noticias/c7-destacada/2025/12/30/complejo-maldonado-abre-sus-puertas-el-viernes/#:~:text=El%20Maldonado%20abrir%C3%A1%20todos%20los%20d%C3%ADas%20de%209%20a%2021%20hs.&text=En%20su%20ingreso%20se%20debe,el%20ingreso%20de%20bebidas%20alcoh%C3%B3licas. | H5: =IF(C5="", "", IFERROR(VLOOKUP(C5, 'Tabla 2'!$A$2:$D$298, 2, FALSE), "")) -> Local BB | I5: =IF(C5="", "", IFERROR(VLOOKUP(C5, 'Tabla 2'!$A$2:$D$298, 3, FALSE), "")) -> 1 | J5: =IF(C5="", "", IFERROR(VLOOKUP(C5, 'Tabla 2'!$A$2:$D$298, 4, FALSE), "")) -> 5000000 | K5: Positivo | L5: TRUE | M5: Sustentabilidad | N5: Relaciones con la Comunidad | O5: No menciona | P5: 1
A6: 46024 | B6: El balneario Maldonado ya tiene todo preparado para la inauguración de temporada 2026 | C6: 0291 Noticias | D6: Espontánea | E6: Orgánica | F6: Preparativos finales para la inauguración de la temporada 2026 en el balneario Maldonado. | G6: https://0291.com.ar/el-balneario-maldonado-ya-tiene-todo-preparado-para-la-inauguracion-de-temporada-2026/ | H6: =IF(C6="", "", IFERROR(VLOOKUP(C6, 'Tabla 2'!$A$2:$D$298, 2, FALSE), "")) -> Local BB | I6: =IF(C6="", "", IFERROR(VLOOKUP(C6, 'Tabla 2'!$A$2:$D$298, 3, FALSE), "")) -> 3 | J6: =IF(C6="", "", IFERROR(VLOOKUP(C6, 'Tabla 2'!$A$2:$D$298, 4, FALSE), "")) -> 0 | K6: Positivo | L6: TRUE | M6: Sustentabilidad | N6: Relaciones con la Comunidad | O6: No menciona | P6: 1
A7: 46024 | B7: El balneario Maldonado habilitó la temporada 2026 | C7: Café x Medio | D7: Espontánea | E7: Orgánica | F7: Confirmación de la habilitación de la temporada 2026 en el balneario Maldonado. | G7: https://cafexmedio.com.ar/locales/el-balneario-maldonado-habilito-la-temporada-2026/ | H7: =IF(C7="", "", IFERROR(VLOOKUP(C7, 'Tabla 2'!$A$2:$D$298, 2, FALSE), "")) -> Local BB | I7: =IF(C7="", "", IFERROR(VLOOKUP(C7, 'Tabla 2'!$A$2:$D$298, 3, FALSE), "")) -> 2 | J7: =IF(C7="", "", IFERROR(VLOOKUP(C7, 'Tabla 2'!$A$2:$D$298, 4, FALSE), "")) -> 0 | K7: Positivo | L7: TRUE | M7: Sustentabilidad | N7: Relaciones con la Comunidad | O7: No menciona | P7: 1
A8: 46024 | B8: El complejo recreativo Maldonado reabre sus puertas para la temporada 2026 | C8: ArgenSUR | D8: Espontánea | E8: Orgánica | F8: Anuncio de la reapertura del complejo recreativo Maldonado para la temporada de verano 2026. | G8: https://argensur.com.ar/publicacion/22822/el-complejo-recreativo-maldonado-reabre-sus-puertas-para-la-temporada-2026/ | H8: =IF(C8="", "", IFERROR(VLOOKUP(C8, 'Tabla 2'!$A$2:$D$298, 2, FALSE), "")) -> Generalista Nacional | I8: =IF(C8="", "", IFERROR(VLOOKUP(C8, 'Tabla 2'!$A$2:$D$298, 3, FALSE), "")) -> 3 | J8: =IF(C8="", "", IFERROR(VLOOKUP(C8, 'Tabla 2'!$A$2:$D$298, 4, FALSE), "")) -> 0 | K8: Positivo | L8: TRUE | M8: Sustentabilidad | N8: Relaciones con la Comunidad | O8: No menciona | P8: 1
A9: 46024 | B9: Bahía Blanca: el balneario Maldonado habilitó la temporada 2026 | C9: Mega 97.5 | D9: Espontánea | E9: Orgánica | F9: Confirmación de la habilitación de la temporada 2026 en el balneario Maldonado. | G9: https://mega975.com.ar/bahia-blanca-el-balneario-maldonado-habilito-la-temporada-2026/ | H9: =IF(C9="", "", IFERROR(VLOOKUP(C9, 'Tabla 2'!$A$2:$D$298, 2, FALSE), "")) -> Generalista Nacional | I9: =IF(C9="", "", IFERROR(VLOOKUP(C9, 'Tabla 2'!$A$2:$D$298, 3, FALSE), "")) -> 3 | J9: =IF(C9="", "", IFERROR(VLOOKUP(C9, 'Tabla 2'!$A$2:$D$298, 4, FALSE), "")) -> 0 | K9: Positivo | L9: TRUE | M9: Sustentabilidad | N9: Relaciones con la Comunidad | O9: No menciona | P9: 1
A10: 46024 | B10: Centro Industrial y Logístico | C10: Bahía Productiva | D10: Espontánea | E10: =IF(OR(D10="Espontánea", D10="Reactiva"), "Orgánica", "") -> Orgánica | F10: Información de interés sobre la industria local. | G10: https://bahiaproductiva.com/info-de-interes/industria/ | H10: =IF(C10="", "", IFERROR(VLOOKUP(C10, 'Tabla 2'!$A$2:$D$298, 2, FALSE), "")) -> Local BB | I10: =IF(C10="", "", IFERROR(VLOOKUP(C10, 'Tabla 2'!$A$2:$D$298, 3, FALSE), "")) -> 3 | J10: =IF(C10="", "", IFERROR(VLOOKUP(C10, 'Tabla 2'!$A$2:$D$298, 4, FALSE), "")) -> 0 | K10: Positivo | L10: TRUE | M10: Proveedor Estratégico | N10: Cadena de Valor y Sectores | O10: No menciona | P10: 1
A11: 46024 | B11: Bahía Blanca | C11: Bahía Productiva | D11: Espontánea | E11: =IF(OR(D11="Espontánea", D11="Reactiva"), "Orgánica", "") -> Orgánica | F11: Información de interés general sobre la ciudad de Bahía Blanca. | G11: https://bahiaproductiva.com/info-de-interes/bahia-blanca/ | H11: =IF(C11="", "", IFERROR(VLOOKUP(C11, 'Tabla 2'!$A$2:$D$298, 2, FALSE), "")) -> Local BB | I11: =IF(C11="", "", IFERROR(VLOOKUP(C11, 'Tabla 2'!$A$2:$D$298, 3, FALSE), "")) -> 3 | J11: =IF(C11="", "", IFERROR(VLOOKUP(C11, 'Tabla 2'!$A$2:$D$298, 4, FALSE), "")) -> 0 | K11: Positivo | L11: TRUE | M11: Sustentabilidad | N11: Relaciones con la Comunidad | O11: No menciona | P11: 1
A12: 46027 | B12: Sanar después de la tormenta: reconstruir una comunidad cuando el daño no se ve | C12: Visión Sustentable | D12: Proactiva | E12: Orgánica | F12: Reflexión sobre la reconstrucción comunitaria y el impacto invisible tras una tormenta. | G12: https://www.visionsustentable.com/2026/01/05/sanar-despues-de-la-tormenta-reconstruir-una-comunidad-cuando-el-dano-no-se-ve/ | H12: =IF(C12="", "", IFERROR(VLOOKUP(C12, 'Tabla 2'!$A$2:$D$298, 2, FALSE), "")) -> Sustentabilidad Nacional | I12: =IF(C12="", "", IFERROR(VLOOKUP(C12, 'Tabla 2'!$A$2:$D$298, 3, FALSE), "")) -> 1 | J12: =IF(C12="", "", IFERROR(VLOOKUP(C12, 'Tabla 2'!$A$2:$D$298, 4, FALSE), "")) -> 600000 | K12: Positivo | L12: TRUE | M12: Sustentabilidad | N12: Relaciones con la Comunidad | O12: No menciona | P12: 1
A13: 46028 | B13: Las acciones llevadas a cabo por la Dirección Institucional | C13: Tiempo Industrial | D13: Espontánea | E13: Orgánica | F13: La inundación del 7 de marzo afectó las instalaciones de la UIBB. Además, muchas pymes estuvieron complicadas, lo que motivó a repensar la planificación anual. | G13: https://sentinel.globalnewsgroup.com/ver-noticia?ysTe9aO_9pWtqaYiIJ0yHIzJCBqMZA1s0CXXdYARVPY | H13: =IF(C13="", "", IFERROR(VLOOKUP(C13, 'Tabla 2'!$A$2:$D$298, 2, FALSE), "")) -> Local BB | I13: =IF(C13="", "", IFERROR(VLOOKUP(C13, 'Tabla 2'!$A$2:$D$298, 3, FALSE), "")) -> 3 | J13: =IF(C13="", "", IFERROR(VLOOKUP(C13, 'Tabla 2'!$A$2:$D$298, 4, FALSE), "")) -> 0 | K13: Positivo | L13: FALSE | M13: Institucional | N13: Generalidades | O13: No menciona | P13: 1
A14: 46059 | B14: Cómo funciona la biblia de la industria química y petroquímica para dejar de contaminar | C14: Economía Sustentable | D14: Espontánea | E14: =IF(OR(D14="Espontánea", D14="Reactiva"), "Orgánica", "") -> Orgánica | F14: Artículo sobre el funcionamiento de la guía de la industria química y petroquímica para reducir la contaminación. | G14: https://economiasustentable.com/noticias/como-funciona-la-biblia-de-la-industria-quimica-y-petroquimica-para-dejar-de-contaminar/ | H14: =IF(C14="", "", IFERROR(VLOOKUP(C14, 'Tabla 2'!$A$2:$D$298, 2, FALSE), "")) -> Sustentabilidad Nacional | I14: =IF(C14="", "", IFERROR(VLOOKUP(C14, 'Tabla 2'!$A$2:$D$298, 3, FALSE), "")) -> 3 | J14: =IF(C14="", "", IFERROR(VLOOKUP(C14, 'Tabla 2'!$A$2:$D$298, 4, FALSE), "")) -> 0 | K14: Positivo | L14: TRUE | M14: Sustentabilidad | N14: Estrategia ESG | O14: No menciona | P14: 1
A15: 46059 | B15: Hoy la sostenibilidad pasa por sostener el empleo y la productividad y eso tiene que ver con competitividad | C15: Sustenomics | D15: Espontánea | E15: Orgánica | F15: Reflexión sobre cómo la sostenibilidad actual se relaciona con el mantenimiento del empleo, la productividad y la competitividad. | G15: https://sustenomics.com/hoy-la-sostenibilidad-pasa-por-sostener-el-empleo-y-la-productividad-y-eso-tiene-que-ver-con-competitividad/ | H15: =IF(C15="", "", IFERROR(VLOOKUP(C15, 'Tabla 2'!$A$2:$D$298, 2, FALSE), "")) -> Sustentabilidad Nacional | I15: =IF(C15="", "", IFERROR(VLOOKUP(C15, 'Tabla 2'!$A$2:$D$298, 3, FALSE), "")) -> 1 | J15: =IF(C15="", "", IFERROR(VLOOKUP(C15, 'Tabla 2'!$A$2:$D$298, 4, FALSE), "")) -> 700000 | K15: Positivo | L15: TRUE | M15: Sustentabilidad | N15: Estrategia ESG | O15: No menciona | P15: 1
A16: 46062 | B16: Guillermo Petracci, de Unipar: "El desarrollo de quienes forman Unipar es nuestra prioridad" | C16: Mercado | D16: Proactiva | E16: Orgánica | F16: Libro Blanco de RSE | G16: https://drive.google.com/file/d/1TOPVGerlf-EtMckPhQHK7da1fSrz-1M6/view?usp=sharing | H16: =IF(C16="", "", IFERROR(VLOOKUP(C16, 'Tabla 2'!$A$2:$D$298, 2, FALSE), "")) -> Negocio Nacional | I16: =IF(C16="", "", IFERROR(VLOOKUP(C16, 'Tabla 2'!$A$2:$D$298, 3, FALSE), "")) -> 1 | J16: =IF(C16="", "", IFERROR(VLOOKUP(C16, 'Tabla 2'!$A$2:$D$298, 4, FALSE), "")) -> 500000 | K16: Positivo | L16: TRUE | M16: Institucional | N16: Marca Empleadora/RRHH | O16: Guillermo Petracci | P16: 1
A17: 46064 | B17: Premio Conciencia: una mirada multisectorial para reconocer impacto real | C17: NBS | D17: Proactiva | E17: Orgánica | F17: Cobertura sobre el Premio Conciencia y su enfoque multisectorial para reconocer el impacto real. | G17: https://nbs.ar/premio-conciencia-una-mirada-multisectorial-para-reconocer-impacto-real/ | H17: =IF(C17="", "", IFERROR(VLOOKUP(C17, 'Tabla 2'!$A$2:$D$298, 2, FALSE), "")) -> Generalista Nacional | I17: =IF(C17="", "", IFERROR(VLOOKUP(C17, 'Tabla 2'!$A$2:$D$298, 3, FALSE), "")) -> 3 | J17: =IF(C17="", "", IFERROR(VLOOKUP(C17, 'Tabla 2'!$A$2:$D$298, 4, FALSE), "")) -> 0 | K17: Positivo | L17: TRUE | M17: Sustentabilidad | N17: Estrategia ESG | O17: No menciona | P17: 1
A18: 46064 | B18: Revista N° 351 | C18: NBS | D18: Proactiva | E18: Orgánica | F18: Publicación de la edición N° 351 de la revista. | G18: https://nbs.ar/project/revista-no-351/ | H18: =IF(C18="", "", IFERROR(VLOOKUP(C18, 'Tabla 2'!$A$2:$D$298, 2, FALSE), "")) -> Generalista Nacional | I18: =IF(C18="", "", IFERROR(VLOOKUP(C18, 'Tabla 2'!$A$2:$D$298, 3, FALSE), "")) -> 3 | J18: =IF(C18="", "", IFERROR(VLOOKUP(C18, 'Tabla 2'!$A$2:$D$298, 4, FALSE), "")) -> 0 | K18: Positivo | L18: FALSE | M18: Institucional | N18: Generalidades | O18: No menciona | P18: 1
A19: 46065 | B19: Inauguración de nuevos servicios de oncología y hematología en el Hospital Municipal | C19: 0291 Noticias | D19: Espontánea | E19: =IF(OR(D19="Espontánea", D19="Reactiva"), "Orgánica", "") -> Orgánica | F19: Noticia sobre la inauguración de las nuevas áreas de oncología y hematología en el Hospital Municipal. | G19: https://0291.com.ar/inauguracion-de-nuevos-servicios-de-oncologia-y-hematologia-en-el-hospital-municipal/ | H19: =IF(C19="", "", IFERROR(VLOOKUP(C19, 'Tabla 2'!$A$2:$D$298, 2, FALSE), "")) -> Local BB | I19: =IF(C19="", "", IFERROR(VLOOKUP(C19, 'Tabla 2'!$A$2:$D$298, 3, FALSE), "")) -> 3 | J19: =IF(C19="", "", IFERROR(VLOOKUP(C19, 'Tabla 2'!$A$2:$D$298, 4, FALSE), "")) -> 0 | K19: Positivo | M19: Sustentabilidad | N19: Relaciones con la Comunidad | O19: No menciona | P19: 1
A20: 46065 | B20: El Hospital Municipal inauguró los nuevos servicios de oncología y hematología | C20: Frente a Cano | D20: Espontánea | E20: =IF(OR(D20="Espontánea", D20="Reactiva"), "Orgánica", "") -> Orgánica | F20: Reporte de la apertura de los nuevos servicios de oncología y hematología en el Hospital Municipal. | G20: https://frenteacano.com.ar/el-hospital-municipal-inauguro-los-nuevos-servicios-de-oncologia-y-hematologia/ | H20: =IF(C20="", "", IFERROR(VLOOKUP(C20, 'Tabla 2'!$A$2:$D$298, 2, FALSE), "")) -> Local BB | I20: =IF(C20="", "", IFERROR(VLOOKUP(C20, 'Tabla 2'!$A$2:$D$298, 3, FALSE), "")) -> 1 | J20: =IF(C20="", "", IFERROR(VLOOKUP(C20, 'Tabla 2'!$A$2:$D$298, 4, FALSE), "")) -> 800000 | K20: Positivo | L20: FALSE | M20: Sustentabilidad | N20: Relaciones con la Comunidad | O20: No menciona | P20: 1
A21: 46065 | B21: El intendente inauguró los nuevos servicios de oncología y hematología en el Hospital Municipal junto a autoridades y trabajadores de la salud | C21: Ingeniero White | D21: Espontánea | E21: =IF(OR(D21="Espontánea", D21="Reactiva"), "Orgánica", "") -> Orgánica | F21: Cobertura de la inauguración de servicios de salud en el Hospital Municipal por parte del intendente. | G21: https://www.ingenierowhite.com/2026/02/12/el-intendente-inauguro-los-nuevos-servicios-de-oncologia-y-hematologia-en-el-hospital-municipal-junto-a-autoridades-y-trabajadores-de-la-salud/ | H21: =IF(C21="", "", IFERROR(VLOOKUP(C21, 'Tabla 2'!$A$2:$D$298, 2, FALSE), "")) -> Local BB | I21: =IF(C21="", "", IFERROR(VLOOKUP(C21, 'Tabla 2'!$A$2:$D$298, 3, FALSE), "")) -> 1 | J21: =IF(C21="", "", IFERROR(VLOOKUP(C21, 'Tabla 2'!$A$2:$D$298, 4, FALSE), "")) -> 500000 | K21: Positivo | M21: Sustentabilidad | N21: Relaciones con la Comunidad | O21: No menciona | P21: 1
A22: 46065 | B22: Quienes tenían compromisos reales con enfoque de gestión pudieron sostener las agendas de sostenibilidad | C22: Sustenomics | D22: Espontánea | E22: =IF(D22<>"","Orgánica","") -> Orgánica | F22: Artículo sobre cómo los compromisos reales con enfoque de gestión sostuvieron las agendas de sostenibilidad. | G22: https://sustenomics.com/quienes-tenian-compromisos-reales-con-enfoque-de-gestion-pudieron-sostener-las-agendas-de-sostenibilidad/ | H22: =IF(C22="", "", IFERROR(VLOOKUP(C22, 'Tabla 2'!$A$2:$D$298, 2, FALSE), "")) -> Sustentabilidad Nacional | I22: =IF(C22="", "", IFERROR(VLOOKUP(C22, 'Tabla 2'!$A$2:$D$298, 3, FALSE), "")) -> 1 | J22: =IF(C22="", "", IFERROR(VLOOKUP(C22, 'Tabla 2'!$A$2:$D$298, 4, FALSE), "")) -> 700000 | K22: Positivo | L22: TRUE | M22: Sustentabilidad | N22: Estrategia ESG | O22: No menciona | P22: 1
A23: 46068 | B23: Guillermo Petracci de Unipar: la variable ESG actúa como un motor de innovación | C23: Mercado | D23: Proactiva | E23: =IF(D23<>"","Orgánica","") -> Orgánica | F23: Entrevista a Guillermo Petracci sobre cómo la variable ESG actúa como motor de innovación en Unipar. | G23: https://mercado.com.ar/gestion-sustentable/guillermo-petracci-de-unipar-la-variable-esg-actua-como-un-motor-de-innovacion/#:~:text=Asimismo%2C%20el%20desarrollo%20de%20quienes,motor%20de%20nuestra%20excelencia%20operativa. | H23: =IF(C23="", "", IFERROR(VLOOKUP(C23, 'Tabla 2'!$A$2:$D$298, 2, FALSE), "")) -> Negocio Nacional | I23: =IF(C23="", "", IFERROR(VLOOKUP(C23, 'Tabla 2'!$A$2:$D$298, 3, FALSE), "")) -> 1 | J23: =IF(C23="", "", IFERROR(VLOOKUP(C23, 'Tabla 2'!$A$2:$D$298, 4, FALSE), "")) -> 500000 | K23: Positivo | L23: TRUE | M23: Sustentabilidad | N23: Estrategia ESG | O23: Guillermo Petracci | P23: 1
A24: 46075 | B24: El Hospital Municipal consolida su plan director con una ampliación histórica | C24: La Nueva Provincia | D24: Espontánea | E24: =IF(D24<>"","Orgánica","") -> Orgánica | F24: Cobertura sobre la consolidación del plan director y la ampliación histórica del Hospital Municipal. | G24: https://www.lanueva.com/nota/2026-2-22-5-0-25-el-hospital-municipal-consolida-su-plan-director-con-una-ampliacion-historica | H24: =IF(C24="", "", IFERROR(VLOOKUP(C24, 'Tabla 2'!$A$2:$D$298, 2, FALSE), "")) -> Local BB | I24: =IF(C24="", "", IFERROR(VLOOKUP(C24, 'Tabla 2'!$A$2:$D$298, 3, FALSE), "")) -> 1 | J24: =IF(C24="", "", IFERROR(VLOOKUP(C24, 'Tabla 2'!$A$2:$D$298, 4, FALSE), "")) -> 900000 | K24: Positivo | M24: Sustentabilidad | N24: Relaciones con la Comunidad | O24: No menciona | P24: 1
A25: 46075 | B25: El Hospital Municipal consolida su plan director con una ampliación histórica | C25: La Nueva Provincia | D25: Espontánea | E25: =IF(D25<>"","Orgánica","") -> Orgánica | F25: Reporte de noticias a través de la plataforma Sentinel Global News Group. | G25: https://sentinel.globalnewsgroup.com/ver-noticia?8Aa4j7y426naa627XRILnrA-vMW8m9BUZQ5iNg6PrzU | H25: Local BB | I25: 1 | J25: 900000 | K25: Positivo | M25: Sustentabilidad | N25: Relaciones con la Comunidad | O25: No menciona | P25: 1
A26: 46077 | B26: Unipar renueva cargos ejecutivos y refuerza su liderazgo institucional en la región | C26: Norte en Línea | D26: Proactiva | E26: =IF(D26<>"","Orgánica","") -> Orgánica | F26: Información sobre la renovación de cargos ejecutivos y el refuerzo del liderazgo institucional de Unipar en la región. | G26: https://norteenlinea.com/unipar-renueva-cargos-ejecutivos-y-refuerza-su-liderazgo-institucional-en-la-region/ | H26: =IF(C26="", "", IFERROR(VLOOKUP(C26, 'Tabla 2'!$A$2:$D$298, 2, FALSE), "")) -> Generalista Nacional | I26: =IF(C26="", "", IFERROR(VLOOKUP(C26, 'Tabla 2'!$A$2:$D$298, 3, FALSE), "")) -> 3 | J26: =IF(C26="", "", IFERROR(VLOOKUP(C26, 'Tabla 2'!$A$2:$D$298, 4, FALSE), "")) -> 0 | K26: Positivo | L26: TRUE | M26: Institucional | N26: Generalidades | O26: No menciona | P26: 1
A27: 46077 | B27: Sanar después de la tormenta: cómo nació el programa de salud mental de Unipar ante la catástrofe | C27: Sustenomics | D27: Proactiva | E27: =IF(D27<>"","Orgánica","") -> Orgánica | F27: Relato sobre el origen y desarrollo del programa de salud mental de Unipar frente a la catástrofe. | G27: https://sustenomics.com/sanar-despues-de-la-tormenta-como-nacio-el-programa-de-salud-mental-de-unipar-ante-la-catastrofe/ | H27: =IF(C27="", "", IFERROR(VLOOKUP(C27, 'Tabla 2'!$A$2:$D$298, 2, FALSE), "")) -> Sustentabilidad Nacional | I27: =IF(C27="", "", IFERROR(VLOOKUP(C27, 'Tabla 2'!$A$2:$D$298, 3, FALSE), "")) -> 1 | J27: =IF(C27="", "", IFERROR(VLOOKUP(C27, 'Tabla 2'!$A$2:$D$298, 4, FALSE), "")) -> 700000 | K27: Positivo | L27: TRUE | M27: Sustentabilidad | N27: Relaciones con la Comunidad | O27: Guillermo Petracci | P27: 1
A28: 46078 | B28: Unipar reordena su cúpula de recursos humanos y amplía su presencia sectorial regional | C28: Mercado | D28: Proactiva | E28: =IF(D28<>"","Orgánica","") -> Orgánica | F28: Detalles sobre la reorganización de la cúpula de recursos humanos de Unipar y su expansión a nivel regional. | G28: https://mercado.com.ar/talento-y-liderazgo/unipar-reordena-su-cupula-de-recursos-humanos-y-amplia-su-presencia-sectorial-regional/ | H28: =IF(C28="", "", IFERROR(VLOOKUP(C28, 'Tabla 2'!$A$2:$D$298, 2, FALSE), "")) -> Negocio Nacional | I28: =IF(C28="", "", IFERROR(VLOOKUP(C28, 'Tabla 2'!$A$2:$D$298, 3, FALSE), "")) -> 1 | J28: =IF(C28="", "", IFERROR(VLOOKUP(C28, 'Tabla 2'!$A$2:$D$298, 4, FALSE), "")) -> 500000 | K28: Positivo | L28: TRUE | M28: Institucional | N28: Marca Empleadora/RRHH | O28: No menciona | P28: 1
A29: 46079 | B29: Aún en crisis de consumo, las empresas cumplieron con el regalo por vuelta a clases | C29: iProfesional | D29: Proactiva | E29: =IF(D29<>"","Orgánica","") -> Orgánica | F29: Informe sobre cómo las empresas mantuvieron la entrega de regalos por la vuelta a clases a pesar de la crisis de consumo. | G29: https://www.iprofesional.com/management/448966-aun-en-crisis-de-consumo-las-empresas-cumplieron-con-el-regalo-por-vuelta-a-clases | H29: =IF(C29="", "", IFERROR(VLOOKUP(C29, 'Tabla 2'!$A$2:$D$298, 2, FALSE), "")) -> Generalista Nacional | I29: =IF(C29="", "", IFERROR(VLOOKUP(C29, 'Tabla 2'!$A$2:$D$298, 3, FALSE), "")) -> 1 | J29: =IF(C29="", "", IFERROR(VLOOKUP(C29, 'Tabla 2'!$A$2:$D$298, 4, FALSE), "")) -> 800000 | K29: Positivo | L29: TRUE | M29: Institucional | N29: Marca Empleadora/RRHH | O29: Laura Gutierrez | P29: 1
A30: 46082 | B30: El Departamento de |óvenes presentó su agenda de trabajo para este año | C30: La Nueva Provincia | D30: Espontánea | E30: Orgánica | F30: Reporte de noticias a través de la plataforma Sentinel Global News Group. | G30: https://sentinel.globalnewsgroup.com/ver-noticia?fHcvtx0QLhew5hvQz3FRLLPtVBVHDHuBPCa72-z7rp4 | H30: =IF(C30="", "", IFERROR(VLOOKUP(C30, 'Tabla 2'!$A$2:$D$298, 2, FALSE), "")) -> Local BB | I30: =IF(C30="", "", IFERROR(VLOOKUP(C30, 'Tabla 2'!$A$2:$D$298, 3, FALSE), "")) -> 1 | J30: =IF(C30="", "", IFERROR(VLOOKUP(C30, 'Tabla 2'!$A$2:$D$298, 4, FALSE), "")) -> 900000 | K30: Positivo | L30: FALSE | M30: Sustentabilidad | N30: Relaciones con la Comunidad | O30: No menciona | P30: 1
A31: 46082 | B31: Nombramientos corporativos | C31: BAE Negocios | D31: Proactiva | E31: Orgánica | F31: Reporte de noticias a través de la plataforma Sentinel Global News Group. | G31: https://sentinel.globalnewsgroup.com/ver-noticia?KLH4WTlWeg-BLtejvBg9wPCclUS9j6NQh11XkK-m7eE | H31: =IF(C31="", "", IFERROR(VLOOKUP(C31, 'Tabla 2'!$A$2:$D$298, 2, FALSE), "")) -> Negocio Nacional | I31: =IF(C31="", "", IFERROR(VLOOKUP(C31, 'Tabla 2'!$A$2:$D$298, 3, FALSE), "")) -> 1 | J31: =IF(C31="", "", IFERROR(VLOOKUP(C31, 'Tabla 2'!$A$2:$D$298, 4, FALSE), "")) -> 800000 | K31: Positivo | L31: TRUE | M31: Institucional | N31: Generalidades | O31: No menciona | P31: 1
A32: 46083 | B32: Unipar renueva su liderazgo ejecutivo y gana peso institucional en la región | C32: InfoNegocios | D32: Proactiva | E32: Orgánica | F32: Información sobre la renovación del liderazgo ejecutivo de Unipar y su peso institucional en la región. | G32: https://infonegocios.info/infogerentes/unipar-renueva-su-liderazgo-ejecutivo-y-gana-peso-institucional-en-la-region-hr-y-representacion-sectorial-2026-2027#:~:text=de%20marzo%20%7C%202026-,Unipar%20renueva%20su%20liderazgo%20ejecutivo%20y%20gana%20peso%20institucional%20en,c%C3%A1maras%20del%20sector%20qu%C3%ADmico%20sudamericano. | H32: =IF(C32="", "", IFERROR(VLOOKUP(C32, 'Tabla 2'!$A$2:$D$298, 2, FALSE), "")) -> Negocio Nacional | I32: =IF(C32="", "", IFERROR(VLOOKUP(C32, 'Tabla 2'!$A$2:$D$298, 3, FALSE), "")) -> 2 | J32: =IF(C32="", "", IFERROR(VLOOKUP(C32, 'Tabla 2'!$A$2:$D$298, 4, FALSE), "")) -> 0 | K32: Positivo | L32: TRUE | M32: Institucional | N32: Generalidades | O32: No menciona | P32: 1
A33: 46085 | B33: Unipar renueva cargos ejecutivos en la región | C33: EBizLatam | D33: Proactiva | E33: Orgánica | F33: Información sobre la renovación de cargos ejecutivos de Unipar en la región. | G33: https://ebizlatam.com/unipar-renueva-cargos-ejecutivos-en-la-region/ | H33: =IF(C33="", "", IFERROR(VLOOKUP(C33, 'Tabla 2'!$A$2:$D$298, 2, FALSE), "")) -> Generalista Nacional | I33: =IF(C33="", "", IFERROR(VLOOKUP(C33, 'Tabla 2'!$A$2:$D$298, 3, FALSE), "")) -> 3 | J33: =IF(C33="", "", IFERROR(VLOOKUP(C33, 'Tabla 2'!$A$2:$D$298, 4, FALSE), "")) -> 0 | K33: Positivo | L33: TRUE | M33: Institucional | N33: Generalidades | O33: No menciona | P33: 1
A34: 46091 | B34: Un tema que se consolidó en 2025 fue la integridad: la relevancia de tener datos clave | C34: Sustenomics | D34: Proactiva | E34: Orgánica | F34: Artículo sobre la consolidación de la integridad y la relevancia de tener datos clave. | G34: https://sustenomics.com/un-tema-que-se-consolido-en-2025-fue-la-integridad-la-relevancia-de-tener-datos-clave/ | H34: =IF(C34="", "", IFERROR(VLOOKUP(C34, 'Tabla 2'!$A$2:$D$298, 2, FALSE), "")) -> Sustentabilidad Nacional | I34: =IF(C34="", "", IFERROR(VLOOKUP(C34, 'Tabla 2'!$A$2:$D$298, 3, FALSE), "")) -> 1 | J34: =IF(C34="", "", IFERROR(VLOOKUP(C34, 'Tabla 2'!$A$2:$D$298, 4, FALSE), "")) -> 700000 | K34: Positivo | M34: Institucional | N34: Marca Empleadora/RRHH | O34: No menciona | P34: 1
A35: 46092 | B35: Río Negro verificó obra en salina El Gualicho | C35: Cipolletti Digital | D35: Espontánea | E35: Orgánica | F35: Reporte sobre la verificación de obras en la salina El Gualicho por parte de Río Negro. | G35: https://www.cipollettidigital.com.ar/noticias/2026/03/11/75287-rio-negro-verifico-obra-en-salina-el-gualicho | H35: =IF(C35="", "", IFERROR(VLOOKUP(C35, 'Tabla 2'!$A$2:$D$298, 2, FALSE), "")) -> Generalista Nacional | I35: =IF(C35="", "", IFERROR(VLOOKUP(C35, 'Tabla 2'!$A$2:$D$298, 3, FALSE), "")) -> 3 | J35: =IF(C35="", "", IFERROR(VLOOKUP(C35, 'Tabla 2'!$A$2:$D$298, 4, FALSE), "")) -> 0 | K35: Positivo | L35: FALSE | M35: Institucional | N35: Generalidades | O35: No menciona | P35: 1
A36: 46092 | B36: Río Negro verificó obra en salinas El Gualicho | C36: Gobierno de Rio Negro | D36: Espontánea | E36: Orgánica | F36: Reporte oficial sobre la verificación de obras en las salinas El Gualicho. | G36: https://rionegro.gov.ar/articulo/58233/rio-negro-verifico-obra-en-salinas-el-gualicho | H36: =IF(C36="", "", IFERROR(VLOOKUP(C36, 'Tabla 2'!$A$2:$D$298, 2, FALSE), "")) -> Generalista Nacional | I36: =IF(C36="", "", IFERROR(VLOOKUP(C36, 'Tabla 2'!$A$2:$D$298, 3, FALSE), "")) -> 3 | J36: =IF(C36="", "", IFERROR(VLOOKUP(C36, 'Tabla 2'!$A$2:$D$298, 4, FALSE), "")) -> 0 | K36: Positivo | L36: FALSE | M36: Institucional | N36: Generalidades | O36: No menciona | P36: 1
A37: 46092 | B37: Río Negro verificó obra en salina El Gualicho | C37: Informativo Hoy | D37: Espontánea | E37: Orgánica | F37: Reporte sobre la verificación de obras en la salina El Gualicho. | G37: https://informativohoy.com.ar/rio-negro-verifico-obra-en-salina-el-gualicho/ | H37: =IF(C37="", "", IFERROR(VLOOKUP(C37, 'Tabla 2'!$A$2:$D$298, 2, FALSE), "")) -> Generalista Nacional | I37: =IF(C37="", "", IFERROR(VLOOKUP(C37, 'Tabla 2'!$A$2:$D$298, 3, FALSE), "")) -> 3 | J37: =IF(C37="", "", IFERROR(VLOOKUP(C37, 'Tabla 2'!$A$2:$D$298, 4, FALSE), "")) -> 0 | K37: Positivo | L37: FALSE | M37: Institucional | N37: Generalidades | O37: No menciona | P37: 1
A38: 46092 | B38: Salinas del Gualicho: el gobierno inspeccionó obras y controló el impacto ambiental a las empresas | C38: La Mañana Cipolletti | D38: Espontánea | E38: Orgánica | F38: El Gobierno de Río Negro inspeccionó obras y controló el impacto ambiental de las empresas en las salinas. | G38: https://www.lmcipolletti.com/provincia/salinas-del-gualicho-el-gobierno-inspecciono-obras-y-controlo-el-impacto-ambiental-las-empresas-n1231293#:~:text=El%20Gobierno%20de%20R%C3%ADo%20Negro,salinas%20m%C3%A1s%20grandes%20de%20Sudam%C3%A9rica. | H38: =IF(C38="", "", IFERROR(VLOOKUP(C38, 'Tabla 2'!$A$2:$D$298, 2, FALSE), "")) -> Generalista Nacional | I38: =IF(C38="", "", IFERROR(VLOOKUP(C38, 'Tabla 2'!$A$2:$D$298, 3, FALSE), "")) -> 3 | J38: =IF(C38="", "", IFERROR(VLOOKUP(C38, 'Tabla 2'!$A$2:$D$298, 4, FALSE), "")) -> 0 | K38: Positivo | L38: No | M38: Sustentabilidad | N38: Estrategia ESG | O38: No menciona | P38: 1
A39: 46094 | B39: Cuáles son las 70 mejores empresas para trabajar en Argentina en 2026 | C39: Infobae | D39: Proactiva | E39: Orgánica | F39: Artículo sobre las 70 mejores empresas para trabajar en Argentina en 2026. | G39: https://www.infobae.com/tendencias/2026/03/13/cuales-son-las-70-mejores-empresas-para-trabajar-en-argentina-en-2026/ | H39: =IF(C39="", "", IFERROR(VLOOKUP(C39, 'Tabla 2'!$A$2:$D$298, 2, FALSE), "")) -> Generalista Nacional | I39: =IF(C39="", "", IFERROR(VLOOKUP(C39, 'Tabla 2'!$A$2:$D$298, 3, FALSE), "")) -> 1 | J39: =IF(C39="", "", IFERROR(VLOOKUP(C39, 'Tabla 2'!$A$2:$D$298, 4, FALSE), "")) -> 6000000 | K39: Positivo | L39: TRUE | M39: Institucional | N39: Marca Empleadora/RRHH | O39: No menciona | P39: 1
A40: 46094 | B40: Unipar quedó entre los mejores lugares para trabajar en Argentina y se ubicó 21 en el ranking 2026 | C40: Argen Ports web | D40: Proactiva | E40: Orgánica | F40: Unipar fue reconocida en el ranking de los mejores lugares para trabajar en Argentina. | G40: https://argenports.com/nota/unipar-quedo-entre-los-mejores-lugares-para-trabajar-en-argentina-y-se-ubico-21-en-el-ranking-2026/#:~:text=Unipar%20fue%20reconocida%20en%20el,100.000%20personasen%20todo%20el%20pa%C3%ADs. | H40: =IF(C40="", "", IFERROR(VLOOKUP(C40, 'Tabla 2'!$A$2:$D$298, 2, FALSE), "")) -> Local BB | I40: =IF(C40="", "", IFERROR(VLOOKUP(C40, 'Tabla 2'!$A$2:$D$298, 3, FALSE), "")) -> 2 | J40: =IF(C40="", "", IFERROR(VLOOKUP(C40, 'Tabla 2'!$A$2:$D$298, 4, FALSE), "")) -> 0 | K40: Positivo | L40: TRUE | M40: Institucional | N40: Marca Empleadora/RRHH | O40: No menciona | P40: 1
A41: 46094 | B41: Unipar fue reconocida entre los mejores lugares para trabajar en Argentina 2026 por Great Place to Work | C41: Bahía Productiva | D41: Proactiva | E41: Orgánica | F41: Unipar fue reconocida en el ranking de los mejores lugares para trabajar en Argentina. | G41: https://bahiaproductiva.com/2026/03/13/unipar-fue-reconocida-entre-los-mejores-lugares-para-trabajar-en-argentina-2026-porgreat-place-to-work/ | H41: =IF(C41="", "", IFERROR(VLOOKUP(C41, 'Tabla 2'!$A$2:$D$298, 2, FALSE), "")) -> Local BB | I41: =IF(C41="", "", IFERROR(VLOOKUP(C41, 'Tabla 2'!$A$2:$D$298, 3, FALSE), "")) -> 3 | J41: =IF(C41="", "", IFERROR(VLOOKUP(C41, 'Tabla 2'!$A$2:$D$298, 4, FALSE), "")) -> 0 | K41: Positivo | L41: TRUE | M41: Institucional | N41: Marca Empleadora/RRHH | O41: No menciona | P41: 1
A42: 46094 | B42: Cuáles son las 70 mejores empresas para trabajar en Argentina en 2026 | C42: Entre Ríos Digital | D42: Proactiva | E42: Orgánica | F42: Artículo sobre las 70 mejores empresas para trabajar en Argentina en 2026. | G42: https://entreriosdigital.com/cuales-son-las-70-mejores-empresas-para-trabajar-en-argentina-en-2026/ | H42: =IF(C42="", "", IFERROR(VLOOKUP(C42, 'Tabla 2'!$A$2:$D$298, 2, FALSE), "")) | I42: 3 | J42: =IF(C42="", "", IFERROR(VLOOKUP(C42, 'Tabla 2'!$A$2:$D$298, 4, FALSE), "")) | K42: Positivo | L42: TRUE | M42: Institucional | N42: Marca Empleadora/RRHH | O42: No menciona | P42: 1
A43: 46094 | B43: Mejores lugares para trabajar 2026: ranking en Argentina | C43: Polígono Industrial | D43: Proactiva | E43: Orgánica | F43: Ranking de los mejores lugares para trabajar en Argentina en 2026. | G43: https://poligono.com.ar/2026/03/13/mejores-lugares-para-trabajar-2026-ranking-en-argentina/ | H43: =IF(C43="", "", IFERROR(VLOOKUP(C43, 'Tabla 2'!$A$2:$D$298, 2, FALSE), "")) -> Local BB | I43: =IF(C43="", "", IFERROR(VLOOKUP(C43, 'Tabla 2'!$A$2:$D$298, 3, FALSE), "")) -> 3 | J43: =IF(C43="", "", IFERROR(VLOOKUP(C43, 'Tabla 2'!$A$2:$D$298, 4, FALSE), "")) -> 0 | K43: Positivo | L43: TRUE | M43: Institucional | N43: Marca Empleadora/RRHH | O43: No menciona | P43: 1
A44: 46094 | B44: Unipar fue reconocida entre los mejores lugares para trabajar en Argentina | C44: Frente a Cano | D44: Proactiva | E44: Orgánica | F44: Unipar fue reconocida en el ranking de los mejores lugares para trabajar en Argentina. | G44: https://frenteacano.com.ar/unipar-fue-reconocida-entre-los-mejores-lugares-para-trabajar-en-argentina/ | H44: =IF(C44="", "", IFERROR(VLOOKUP(C44, 'Tabla 2'!$A$2:$D$298, 2, FALSE), "")) -> Local BB | I44: =IF(C44="", "", IFERROR(VLOOKUP(C44, 'Tabla 2'!$A$2:$D$298, 3, FALSE), "")) -> 1 | J44: =IF(C44="", "", IFERROR(VLOOKUP(C44, 'Tabla 2'!$A$2:$D$298, 4, FALSE), "")) -> 800000 | K44: Positivo | L44: TRUE | M44: Institucional | N44: Marca Empleadora/RRHH | O44: Guillermo Petracci | P44: 1
A45: 46094 | B45: Unipar fue reconocida entre los mejores lugares para trabajar en Argentina | C45: Futuro Sustentable | D45: Proactiva | E45: Orgánica | F45: Unipar fue reconocida en el ranking de los mejores lugares para trabajar en Argentina. | G45: https://futurosustentable.com.ar/unipar-fue-reconocida-entre-los-mejores-lugares-para-trabajar-en-argentina/ | H45: =IF(C45="", "", IFERROR(VLOOKUP(C45, 'Tabla 2'!$A$2:$D$298, 2, FALSE), "")) -> Sustentabilidad Nacional | I45: =IF(C45="", "", IFERROR(VLOOKUP(C45, 'Tabla 2'!$A$2:$D$298, 3, FALSE), "")) -> 2 | J45: =IF(C45="", "", IFERROR(VLOOKUP(C45, 'Tabla 2'!$A$2:$D$298, 4, FALSE), "")) -> 0 | K45: Positivo | L45: TRUE | M45: Institucional | N45: Marca Empleadora/RRHH | O45: No menciona | P45: 1
A46: 46094 | B46: Unipar fue reconocida entre los mejores lugares para trabajar en Argentina 2026 por Great Place to Work | C46: Ingeniero White | D46: Proactiva | E46: Orgánica | F46: Unipar fue reconocida en el ranking de los mejores lugares para trabajar en Argentina. | G46: https://www.ingenierowhite.com/2026/03/13/unipar-fue-reconocida-entre-los-mejores-lugares-para-trabajar-en-argentina-2026-porgreat-place-to-work/ | H46: =IF(C46="", "", IFERROR(VLOOKUP(C46, 'Tabla 2'!$A$2:$D$298, 2, FALSE), "")) -> Local BB | I46: =IF(C46="", "", IFERROR(VLOOKUP(C46, 'Tabla 2'!$A$2:$D$298, 3, FALSE), "")) -> 1 | J46: =IF(C46="", "", IFERROR(VLOOKUP(C46, 'Tabla 2'!$A$2:$D$298, 4, FALSE), "")) -> 500000 | K46: Positivo | L46: TRUE | M46: Institucional | N46: Marca Empleadora/RRHH | O46: Guillermo Petracci | P46: 1
A47: 46094 | B47: Unipar fue reconocida entre los mejores lugares para trabajar en Argentina 2026 por Great Place to Work | C47: Polígono Industrial | D47: Proactiva | E47: Orgánica | F47: Unipar fue reconocida en el ranking de los mejores lugares para trabajar en Argentina por Great Place to Work. | G47: https://poligono.com.ar/2026/03/13/unipar-fue-reconocida-entre-los-mejores-lugares-para-trabajar-en-argentina-2026-por-great-place-to-work/ | H47: =IF(C47="", "", IFERROR(VLOOKUP(C47, 'Tabla 2'!$A$2:$D$298, 2, FALSE), "")) -> Local BB | I47: =IF(C47="", "", IFERROR(VLOOKUP(C47, 'Tabla 2'!$A$2:$D$298, 3, FALSE), "")) -> 3 | J47: =IF(C47="", "", IFERROR(VLOOKUP(C47, 'Tabla 2'!$A$2:$D$298, 4, FALSE), "")) -> 0 | K47: Positivo | L47: TRUE | M47: Institucional | N47: Marca Empleadora/RRHH | O47: No menciona | P47: 1
A48: 46095 | B48: Ranking: Arcos Dorados, DHL y PedidosYa, mejores empresas para trabajar en Argentina 2026 | C48: iProfesional | D48: Proactiva | E48: Orgánica | F48: Ranking de las mejores empresas para trabajar en Argentina 2026. | G48: https://www.iprofesional.com/management/450137-ranking-arcos-dorados-dhl-y-pedidosya-mejores-empresas-para-trabajar-en-argentina-2026 | H48: =IF(C48="", "", IFERROR(VLOOKUP(C48, 'Tabla 2'!$A$2:$D$298, 2, FALSE), "")) -> Generalista Nacional | I48: =IF(C48="", "", IFERROR(VLOOKUP(C48, 'Tabla 2'!$A$2:$D$298, 3, FALSE), "")) -> 1 | J48: =IF(C48="", "", IFERROR(VLOOKUP(C48, 'Tabla 2'!$A$2:$D$298, 4, FALSE), "")) -> 800000 | K48: Positivo | L48: TRUE | M48: Institucional | N48: Marca Empleadora/RRHH | O48: No menciona | P48: 1
A49: 46097 | B49: Río Negro verificó condiciones ambientales de una obra en salina El Gualicho | C49: Más Rio Negro | D49: Espontánea | E49: =IF(OR(D49="Espontánea", D49="Reactiva"), "Orgánica", "") -> Orgánica | F49: El gobierno de Río Negro verificó las condiciones ambientales de una obra en la salina El Gualicho. | G49: https://www.masrionegro.com/2026/03/16/rio-negro-verifico-condiciones-ambientales-de-una-obra-en-salina-el-gualicho/ | H49: =IF(C49="", "", IFERROR(VLOOKUP(C49, 'Tabla 2'!$A$2:$D$298, 2, FALSE), "")) -> Generalista Nacional | I49: =IF(C49="", "", IFERROR(VLOOKUP(C49, 'Tabla 2'!$A$2:$D$298, 3, FALSE), "")) -> 3 | J49: =IF(C49="", "", IFERROR(VLOOKUP(C49, 'Tabla 2'!$A$2:$D$298, 4, FALSE), "")) -> 0 | K49: Positivo | L49: FALSE | M49: Sustentabilidad | N49: Estrategia ESG | O49: No menciona | P49: 1
A50: 46097 | B50: Unipar: jornada de recolección de semillas | C50: Ingeniero White | D50: Proactiva | E50: Orgánica | F50: Unipar organizó una jornada de recolección de semillas. | G50: https://www.ingenierowhite.com/2026/03/16/unipar-jornada-de-recoleccion-de-semillas/ | H50: =IF(C50="", "", IFERROR(VLOOKUP(C50, 'Tabla 2'!$A$2:$D$298, 2, FALSE), "")) -> Local BB | I50: =IF(C50="", "", IFERROR(VLOOKUP(C50, 'Tabla 2'!$A$2:$D$298, 3, FALSE), "")) -> 1 | J50: =IF(C50="", "", IFERROR(VLOOKUP(C50, 'Tabla 2'!$A$2:$D$298, 4, FALSE), "")) -> 500000 | K50: Positivo | L50: TRUE | M50: Sustentabilidad | N50: Relaciones con la Comunidad | O50: No menciona | P50: 1
A51: 46097 | B51: Industria química y gestión del agua: eficiencia, reutilización y sostenibilidad como ejes estratégicos | C51: Futuro Sustentable | D51: Proactiva | E51: Orgánica | F51: Análisis sobre la industria química y la gestión del agua, enfocándose en la eficiencia, reutilización y sostenibilidad. | G51: https://futurosustentable.com.ar/industria-quimica-y-gestion-del-agua-eficiencia-reutilizacion-y-sostenibilidad-como-ejes-estrategicos/ | H51: =IF(C51="", "", IFERROR(VLOOKUP(C51, 'Tabla 2'!$A$2:$D$298, 2, FALSE), "")) -> Sustentabilidad Nacional | I51: =IF(C51="", "", IFERROR(VLOOKUP(C51, 'Tabla 2'!$A$2:$D$298, 3, FALSE), "")) -> 2 | J51: =IF(C51="", "", IFERROR(VLOOKUP(C51, 'Tabla 2'!$A$2:$D$298, 4, FALSE), "")) -> 0 | K51: Positivo | L51: TRUE | M51: Sustentabilidad | N51: Estrategia ESG | O51: No menciona | P51: 1
A52: 46097 | B52: Designaciones en Mercado Libre, BASF y Eresagro | C52: Talento y Empresa | D52: Proactiva | E52: Orgánica | F52: Nuevas designaciones corporativas en Mercado Libre, BASF y Eresagro. | G52: https://www.talentoyempresa.com.ar/article/designaciones-en-mercado-libre-basf-y-eresagro | H52: =IF(C52="", "", IFERROR(VLOOKUP(C52, 'Tabla 2'!$A$2:$D$298, 2, FALSE), "")) -> Generalista Nacional | I52: =IF(C52="", "", IFERROR(VLOOKUP(C52, 'Tabla 2'!$A$2:$D$298, 3, FALSE), "")) -> 3 | J52: =IF(C52="", "", IFERROR(VLOOKUP(C52, 'Tabla 2'!$A$2:$D$298, 4, FALSE), "")) -> 0 | K52: Positivo | L52: TRUE | M52: Institucional | N52: Generalidades | O52: No menciona | P52: 1
A53: 46110 | B53: Construir cultura con foco en las personas, incluso en tiempos desafiantes | C53: La Nueva Provincia | D53: Proactiva | E53: =IF(D53="","","Orgánica") -> Orgánica | F53: Reporte de noticias a través de la plataforma GlobalNews. | G53: https://archivos.globalnews.com.ar/682/746/364/29.03.2026_1910_14eeaf0.jpg | H53: =IF(C53="", "", IFERROR(VLOOKUP(C53, 'Tabla 2'!$A$2:$D$298, 2, FALSE), "")) -> Local BB | I53: =IF(C53="", "", IFERROR(VLOOKUP(C53, 'Tabla 2'!$A$2:$D$298, 3, FALSE), "")) -> 1 | J53: =IF(C53="", "", IFERROR(VLOOKUP(C53, 'Tabla 2'!$A$2:$D$298, 4, FALSE), "")) -> 900000 | K53: Positivo | L53: TRUE | M53: Institucional | N53: Marca Empleadora/RRHH | O53: No menciona | P53: 1
A54: 46123 | B54: Unipar y Bahía Blanca, una historia compartida | C54: La Nueva Provincia | D54: Proactiva | E54: =IF(D54="","","Orgánica") -> Orgánica | F54: Artículo sobre la historia compartida entre Unipar y la ciudad de Bahía Blanca. | G54: https://www.lanueva.com/puntaalta/nota/2026-4-11-4-0-36-unipar-y-bahia-blanca-una-historia-compartida | H54: =IF(C54="", "", IFERROR(VLOOKUP(C54, 'Tabla 2'!$A$2:$D$298, 2, FALSE), "")) -> Local BB | I54: =IF(C54="", "", IFERROR(VLOOKUP(C54, 'Tabla 2'!$A$2:$D$298, 3, FALSE), "")) -> 1 | J54: =IF(C54="", "", IFERROR(VLOOKUP(C54, 'Tabla 2'!$A$2:$D$298, 4, FALSE), "")) -> 900000 | K54: Positivo | L54: TRUE | M54: Institucional | N54: Generalidades | O54: No menciona | P54: 1
A55: 46123 | B55: Unipar y Bahía Blanca, una historia compartida | C55: La Nueva Provincia | D55: Proactiva | E55: =IF(D55="","","Orgánica") -> Orgánica | F55: Reporte de noticias a través de la plataforma Sentinel Global News Group. | G55: https://sentinel.globalnewsgroup.com/ver-noticia?vd1B4HLJkCxKYgAKED0caHf9oI-M7NdPd_gAyaMpgBY | H55: =IF(C55="", "", IFERROR(VLOOKUP(C55, 'Tabla 2'!$A$2:$D$298, 2, FALSE), "")) -> Local BB | I55: =IF(C55="", "", IFERROR(VLOOKUP(C55, 'Tabla 2'!$A$2:$D$298, 3, FALSE), "")) -> 1 | J55: =IF(C55="", "", IFERROR(VLOOKUP(C55, 'Tabla 2'!$A$2:$D$298, 4, FALSE), "")) -> 900000 | K55: Positivo | L55: TRUE | M55: Institucional | N55: Generalidades | O55: No menciona | P55: 1
A56: 46126 | B56: Pueyrredón y un nuevo club de pie con su nueva cancha de básquet | C56: 0291 Noticias | D56: Espontánea | E56: =IF(D56="","","Orgánica") -> Orgánica | F56: Cobertura sobre la inauguración de la nueva cancha de básquet del club Pueyrredón. | G56: https://0291.com.ar/pueyrredon-y-un-nuevo-club-de-pie-con-su-nueva-cancha-de-basquet/ | H56: =IF(C56="", "", IFERROR(VLOOKUP(C56, 'Tabla 2'!$A$2:$D$298, 2, FALSE), "")) -> Local BB | I56: =IF(C56="", "", IFERROR(VLOOKUP(C56, 'Tabla 2'!$A$2:$D$298, 3, FALSE), "")) -> 3 | J56: =IF(C56="", "", IFERROR(VLOOKUP(C56, 'Tabla 2'!$A$2:$D$298, 4, FALSE), "")) -> 0 | K56: Positivo | L56: TRUE | M56: Sustentabilidad | N56: Relaciones con la Comunidad | O56: No menciona | P56: 1
A57: 46126 | B57: Clubes de pie: el Municipio reconstruirá los gimnasios derrumbados y fortalecerá a instituciones | C57: ArgenSUR | D57: Espontánea | E57: =IF(D57="","","Orgánica") -> Orgánica | F57: Información sobre el programa municipal Clubes de pie para reconstruir instituciones afectadas por el temporal. | G57: https://argensur.com.ar/publicacion/9166/clubes-de-pie--el-municipio-reconstruira-los-gimnasios-derrumbados-y-fortalecera-a-instituciones-que-hayan-sufrido-afecciones-por-el-temporal | H57: =IF(C57="", "", IFERROR(VLOOKUP(C57, 'Tabla 2'!$A$2:$D$298, 2, FALSE), "")) -> Generalista Nacional | I57: =IF(C57="", "", IFERROR(VLOOKUP(C57, 'Tabla 2'!$A$2:$D$298, 3, FALSE), "")) -> 3 | J57: =IF(C57="", "", IFERROR(VLOOKUP(C57, 'Tabla 2'!$A$2:$D$298, 4, FALSE), "")) -> 0 | K57: Positivo | L57: TRUE | M57: Sustentabilidad | N57: Relaciones con la Comunidad | O57: No menciona | P57: 1
A58: 46126 | B58: Tras la inundación, el club Pueyrredón inauguró obras clave de recuperación | C58: Canal 7 Bahia Blanca | D58: Espontánea | E58: =IF(D58="","","Orgánica") -> Orgánica | F58: Reporte sobre la inauguración de obras de recuperación en el club Pueyrredón tras las inundaciones. | G58: https://www.canalsiete.com.ar/c7-noticias/c7-otras-destacadas/2026/04/14/tras-la-inundacion-el-club-pueyrredon-inauguro-obras-clave-de-recuperacion/ | H58: =IF(C58="", "", IFERROR(VLOOKUP(C58, 'Tabla 2'!$A$2:$D$298, 2, FALSE), "")) -> Local BB | I58: =IF(C58="", "", IFERROR(VLOOKUP(C58, 'Tabla 2'!$A$2:$D$298, 3, FALSE), "")) -> 1 | J58: =IF(C58="", "", IFERROR(VLOOKUP(C58, 'Tabla 2'!$A$2:$D$298, 4, FALSE), "")) -> 5000000 | K58: Positivo | L58: TRUE | M58: Sustentabilidad | N58: Relaciones con la Comunidad | O58: No menciona | P58: 1
A59: 46126 | B59: Pueyrredón se suma a la recuperación: 64 clubes ya fueron asistidos por el programa Clubes de pie | C59: De la Bahia | D59: Espontánea | E59: =IF(D59="","","Orgánica") -> Orgánica | F59: Noticia sobre la asistencia del programa Clubes de pie a 64 instituciones, incluyendo al club Pueyrredón. | G59: https://www.delabahia.com.ar/pueyrredon-se-suma-a-la-recuperacion-64-clubes-ya-fueron-asistidos-por-el-programa-clubes-de-pie/ | H59: =IF(C59="", "", IFERROR(VLOOKUP(C59, 'Tabla 2'!$A$2:$D$298, 2, FALSE), "")) -> Local BB | I59: =IF(C59="", "", IFERROR(VLOOKUP(C59, 'Tabla 2'!$A$2:$D$298, 3, FALSE), "")) -> 3 | J59: =IF(C59="", "", IFERROR(VLOOKUP(C59, 'Tabla 2'!$A$2:$D$298, 4, FALSE), "")) -> 0 | K59: Positivo | L59: TRUE | M59: Sustentabilidad | N59: Relaciones con la Comunidad | O59: No menciona | P59: 1
A60: 46126 | B60: Programa Clubes de pie: Pueyrredón también inauguró obras | C60: Frente a Cano | D60: Espontánea | E60: =IF(D60="","","Orgánica") -> Orgánica | F60: Cobertura de la inauguración de obras en el club Pueyrredón como parte del programa Clubes de pie. | G60: https://frenteacano.com.ar/programa-clubes-de-pie-pueyrredon-tambien-inauguro-obras/ | H60: =IF(C60="", "", IFERROR(VLOOKUP(C60, 'Tabla 2'!$A$2:$D$298, 2, FALSE), "")) -> Local BB | I60: =IF(C60="", "", IFERROR(VLOOKUP(C60, 'Tabla 2'!$A$2:$D$298, 3, FALSE), "")) -> 1 | J60: =IF(C60="", "", IFERROR(VLOOKUP(C60, 'Tabla 2'!$A$2:$D$298, 4, FALSE), "")) -> 800000 | K60: Positivo | L60: TRUE | M60: Sustentabilidad | N60: Relaciones con la Comunidad | O60: No menciona | P60: 1
A61: 46126 | B61: Pueyrredón se suma a la recuperación con Unipar como padrino: 64 clubes ya fueron asistidos por el programa Clubes de Pie | C61: Ingeniero White | D61: Espontánea | E61: =IF(D61="","","Orgánica") -> Orgánica | F61: El club Pueyrredón inaugura obras de recuperación tras la tormenta con el apadrinamiento de Unipar en el marco del programa Clubes de Pie. | G61: https://www.ingenierowhite.com/2026/04/14/pueyrredon-se-suma-a-la-recuperacion-con-unipar-como-padrino-64-clubes-ya-fueron-asistidos-por-el-programa-clubes-de-pie/ | H61: =IF(C61="", "", IFERROR(VLOOKUP(C61, 'Tabla 2'!$A$2:$D$298, 2, FALSE), "")) -> Local BB | I61: =IF(C61="", "", IFERROR(VLOOKUP(C61, 'Tabla 2'!$A$2:$D$298, 3, FALSE), "")) -> 1 | J61: =IF(C61="", "", IFERROR(VLOOKUP(C61, 'Tabla 2'!$A$2:$D$298, 4, FALSE), "")) -> 500000 | K61: Positivo | L61: TRUE | M61: Sustentabilidad | N61: Relaciones con la Comunidad | O61: No menciona | P61: 1
A62: 46126 | B62: Clubes de pie: Pueyrredón presentó las obras de en el Vicente Palermo | C62: La Nueva Provincia | D62: Espontánea | E62: =IF(D62="","","Orgánica") -> Orgánica | F62: Pueyrredón presentó las obras realizadas en el estadio Vicente Palermo a través del programa Clubes de Pie. | G62: https://www.lanueva.com/nota/2026-4-14-12-11-0-clubes-de-pie-pueyrredon-presento-las-obras-de-en-el-vicente-palermo | H62: =IF(C62="", "", IFERROR(VLOOKUP(C62, 'Tabla 2'!$A$2:$D$298, 2, FALSE), "")) -> Local BB | I62: =IF(C62="", "", IFERROR(VLOOKUP(C62, 'Tabla 2'!$A$2:$D$298, 3, FALSE), "")) -> 1 | J62: =IF(C62="", "", IFERROR(VLOOKUP(C62, 'Tabla 2'!$A$2:$D$298, 4, FALSE), "")) -> 900000 | K62: Positivo | L62: TRUE | M62: Sustentabilidad | N62: Relaciones con la Comunidad | O62: No menciona | P62: 1
A63: 46126 | B63: Pueyrredón se suma a la recuperación: 64 clubes ya fueron asistidos por el programa Clubes de Pie | C63: Portal Bahiense | D63: Espontánea | E63: =IF(D63="","","Orgánica") -> Orgánica | F63: Pueyrredón se recupera tras el temporal y se suma a los 64 clubes asistidos por el programa Clubes de Pie. | G63: https://portalbahiense.com.ar/pueyrredon-se-suma-a-la-recuperacion-64-clubes-ya-fueron-asistidos-por-el-programa-clubes-de-pie/ | H63: {=_xlfn.XLOOKUP(C63, 'Tabla 2'!A:A, 'Tabla 2'!B:B, "")} -> Local BB | I63: {=_xlfn.XLOOKUP(C63, 'Tabla 2'!A:A, 'Tabla 2'!C:C, "")} -> 3 | J63: {=_xlfn.XLOOKUP(C63, 'Tabla 2'!A:A, 'Tabla 2'!D:D, "")} -> 0 | K63: Positivo | L63: TRUE | M63: Sustentabilidad | N63: Relaciones con la Comunidad | O63: No menciona | P63: 1
A64: 46126 | B64: Pueyrredón se suma a la recuperación: 64 clubes ya fueron asistidos por el programa Clubes de Pie | C64: BVC Noticias | D64: Espontánea | E64: =IF(D64="","","Orgánica") -> Orgánica | F64: Pueyrredón se recupera tras el temporal y se suma a los 64 clubes asistidos por el programa Clubes de Pie. | G64: https://bvcnoticias.com.ar/2026/04/pueyrredon-se-suma-a-la-recuperacion-64-clubes-ya-fueron-asistidos-por-el-programa-clubes-de-pie/ | H64: =IF(C64="", "", IFERROR(VLOOKUP(C64, 'Tabla 2'!$A$2:$D$298, 2, FALSE), "")) -> Local BB | I64: =IF(C64="", "", IFERROR(VLOOKUP(C64, 'Tabla 2'!$A$2:$D$298, 3, FALSE), "")) -> 1 | J64: =IF(C64="", "", IFERROR(VLOOKUP(C64, 'Tabla 2'!$A$2:$D$298, 4, FALSE), "")) -> 1000000 | K64: Positivo | L64: TRUE | M64: Sustentabilidad | N64: Relaciones con la Comunidad | O64: No menciona | P64: 1
A65: 46126 | B65: Pueyrredón inauguró obras en el marco del programa Clubes de Pie: "Es un empujón enorme" | C65: Urbana 93.9 | D65: Espontánea | E65: =IF(D65="","","Orgánica") -> Orgánica | F65: El club Pueyrredón inauguró obras de infraestructura con el apoyo del programa Clubes de Pie, destacando el gran impulso recibido. | G65: https://urbana939.com.ar/pueyrredon-inauguro-obras-en-el-marco-del-programa-clubes-de-pie-es-un-empujon-enorme/ | H65: =IF(C65="", "", IFERROR(VLOOKUP(C65, 'Tabla 2'!$A$2:$D$298, 2, FALSE), "")) -> Generalista Nacional | I65: =IF(C65="", "", IFERROR(VLOOKUP(C65, 'Tabla 2'!$A$2:$D$298, 3, FALSE), "")) -> 3 | J65: =IF(C65="", "", IFERROR(VLOOKUP(C65, 'Tabla 2'!$A$2:$D$298, 4, FALSE), "")) -> 0 | K65: Positivo | L65: TRUE | M65: Sustentabilidad | N65: Relaciones con la Comunidad | O65: No menciona | P65: 1
A66: 46126 | B66: Clubes de pie: Con una inversión de 33 millones de pesos, Pueyrredón inauguró sus nuevas instalaciones | C66: LU 3 Digital | D66: Espontánea | E66: =IF(D66="","","Orgánica") -> Orgánica | F66: Con una inversión de 33 millones de pesos, el club Pueyrredón inauguró sus nuevas instalaciones gracias al programa Clubes de Pie. | G66: https://lu3digital.com.ar/clubes-de-pie-con-una-inversion-de-33-millones-de-pesos-pueyrredon-inauguro-sus-nuevas-instalaciones/ | H66: =IF(C66="", "", IFERROR(VLOOKUP(C66, 'Tabla 2'!$A$2:$D$298, 2, FALSE), "")) -> Local BB | I66: =IF(C66="", "", IFERROR(VLOOKUP(C66, 'Tabla 2'!$A$2:$D$298, 3, FALSE), "")) -> 3 | J66: =IF(C66="", "", IFERROR(VLOOKUP(C66, 'Tabla 2'!$A$2:$D$298, 4, FALSE), "")) -> 0 | K66: Positivo | L66: TRUE | M66: Sustentabilidad | N66: Relaciones con la Comunidad | O66: No menciona | P66: 1
A67: 46126 | B67: Clubes de Pie: Pueyrredón inauguró obras de infraestructura tras la inundación | C67: Que Pasa Ciudad | D67: Espontánea | E67: =IF(D67="","","Orgánica") -> Orgánica | F67: El club Pueyrredón inauguró obras de infraestructura para recuperarse de la inundación, apoyado por el programa Clubes de Pie. | G67: https://quepasaciudad.com.ar/clubes-de-pie-pueyrredon-inauguro-obras-de-infraestructura-tras-la-inundacion/ | H67: =IF(C67="", "", IFERROR(VLOOKUP(C67, 'Tabla 2'!$A$2:$D$298, 2, FALSE), "")) -> Generalista Nacional | I67: =IF(C67="", "", IFERROR(VLOOKUP(C67, 'Tabla 2'!$A$2:$D$298, 3, FALSE), "")) -> 3 | J67: =IF(C67="", "", IFERROR(VLOOKUP(C67, 'Tabla 2'!$A$2:$D$298, 4, FALSE), "")) -> 0 | K67: Positivo | L67: TRUE | M67: Sustentabilidad | N67: Relaciones con la Comunidad | O67: No menciona | P67: 1
A68: 46126 | B68: Pueyrredón y un nuevo club de pie con su nueva cancha de básquet | C68: 0291 Noticias | D68: Espontánea | E68: =IF(D68="","","Orgánica") -> Orgánica | F68: El club Pueyrredón inaugura su nueva cancha de básquet gracias al programa Clubes de Pie. | G68: https://0291.com.ar/pueyrredon-y-un-nuevo-club-de-pie-con-su-nueva-cancha-de-basquet/ | H68: =IF(C68="", "", IFERROR(VLOOKUP(C68, 'Tabla 2'!$A$2:$D$298, 2, FALSE), "")) -> Local BB | I68: =IF(C68="", "", IFERROR(VLOOKUP(C68, 'Tabla 2'!$A$2:$D$298, 3, FALSE), "")) -> 3 | J68: =IF(C68="", "", IFERROR(VLOOKUP(C68, 'Tabla 2'!$A$2:$D$298, 4, FALSE), "")) -> 0 | K68: Positivo | L68: TRUE | M68: Sustentabilidad | N68: Relaciones con la Comunidad | O68: No menciona | P68: 1
A69: 46127 | B69: Las empresas distinguidas en un año agitado | C69: Mercado | D69: Proactiva | E69: =IF(D69="","","Orgánica") -> Orgánica | F69: Documento compartido a través de Google Drive. | G69: https://drive.google.com/file/d/1Cm1nCJAXrtx1ZwRypRzGfSMRYtv5Wpjz/view?usp=sharing | H69: =IF(C69="", "", IFERROR(VLOOKUP(C69, 'Tabla 2'!$A$2:$D$298, 2, FALSE), "")) -> Negocio Nacional | I69: =IF(C69="", "", IFERROR(VLOOKUP(C69, 'Tabla 2'!$A$2:$D$298, 3, FALSE), "")) -> 1 | J69: =IF(C69="", "", IFERROR(VLOOKUP(C69, 'Tabla 2'!$A$2:$D$298, 4, FALSE), "")) -> 500000 | K69: Positivo | L69: TRUE | M69: Institucional | N69: Marca Empleadora/RRHH | O69: No menciona | P69: 1
A70: 46127 | B70: Unipar, protagonista de 2025: la salud mental en la agenda | C70: Mercado | D70: Proactiva | E70: =IF(D70="","","Orgánica") -> Orgánica | F70: Artículo sobre cómo Unipar fue protagonista en 2025 poniendo la salud mental en la agenda. | G70: https://mercado.com.ar/protagonistas/unipar-protagonista-de-2025-la-salud-mental-en-la-agenda | H70: =IF(C70="", "", IFERROR(VLOOKUP(C70, 'Tabla 2'!$A$2:$D$298, 2, FALSE), "")) -> Negocio Nacional | I70: =IF(C70="", "", IFERROR(VLOOKUP(C70, 'Tabla 2'!$A$2:$D$298, 3, FALSE), "")) -> 1 | J70: =IF(C70="", "", IFERROR(VLOOKUP(C70, 'Tabla 2'!$A$2:$D$298, 4, FALSE), "")) -> 500000 | K70: Positivo | L70: TRUE | M70: Institucional | N70: Marca Empleadora/RRHH | O70: No menciona | P70: 1
A71: 46127 | B71: Los CEOs le ponen nota al gobierno | C71: Prensa Económica | D71: Proactiva | E71: =IF(D71="","","Orgánica") -> Orgánica | F71: Reporte de noticias a través de la plataforma Sentinel Global News Group. | G71: https://sentinel.globalnewsgroup.com/ver-noticia?YM6l55J6PPhVFx_tKMuo5nWj9-bZofqDTIaOmMzqpIU | H71: =IF(C71="", "", IFERROR(VLOOKUP(C71, 'Tabla 2'!$A$2:$D$298, 2, FALSE), "")) -> Generalista Nacional | I71: =IF(C71="", "", IFERROR(VLOOKUP(C71, 'Tabla 2'!$A$2:$D$298, 3, FALSE), "")) -> 1 | J71: =IF(C71="", "", IFERROR(VLOOKUP(C71, 'Tabla 2'!$A$2:$D$298, 4, FALSE), "")) -> 200000 | K71: Positivo | L71: TRUE | M71: Institucional | N71: Escenario Político Económico | O71: Guillermo Petracci | P71: 1
A72: 46127 | B72: Empresas B: Argentina en el "top ten" mundial | C72: Prensa Económica | D72: Proactiva | E72: =IF(D72="","","Orgánica") -> Orgánica | F72: Reporte de noticias a través de la plataforma Sentinel Global News Group. | G72: https://sentinel.globalnewsgroup.com/ver-noticia?ZqVcY8CYVc7o2lmGp87B6yGet9Wb_VPLNkfWL7XMovc | H72: =IF(C72="", "", IFERROR(VLOOKUP(C72, 'Tabla 2'!$A$2:$D$298, 2, FALSE), "")) -> Generalista Nacional | I72: =IF(C72="", "", IFERROR(VLOOKUP(C72, 'Tabla 2'!$A$2:$D$298, 3, FALSE), "")) -> 1 | J72: =IF(C72="", "", IFERROR(VLOOKUP(C72, 'Tabla 2'!$A$2:$D$298, 4, FALSE), "")) -> 200000 | K72: Positivo | L72: TRUE | M72: Sustentabilidad | N72: Estrategia ESG | O72: Laura Gutierrez | P72: 1
A73: 46127 | B73: Quién es Quién - 2026 | C73: El Cronista | D73: Proactiva | E73: =IF(D73="","","Orgánica") -> Orgánica | F73: Perfil corporativo de la empresa Unipar en la sección Quién es Quién. | G73: https://www.cronista.com/quien-es-quien/empresa/unipar/ | H73: =IF(C73="", "", IFERROR(VLOOKUP(C73, 'Tabla 2'!$A$2:$D$298, 2, FALSE), "")) -> Negocio Nacional | I73: =IF(C73="", "", IFERROR(VLOOKUP(C73, 'Tabla 2'!$A$2:$D$298, 3, FALSE), "")) -> 1 | J73: =IF(C73="", "", IFERROR(VLOOKUP(C73, 'Tabla 2'!$A$2:$D$298, 4, FALSE), "")) -> 1200000 | K73: Positivo | L73: TRUE | M73: Institucional | N73: Generalidades | O73: Guillermo Petracci | P73: 1
A74: 46127 | B74: Quién es Quién - 2026 | C74: El Cronista | D74: Proactiva | E74: =IF(D74="","","Orgánica") -> Orgánica | F74: Documento compartido a través de Google Drive. | G74: https://drive.google.com/file/d/1MAMyVunXZU1n06GOMh8vkvepeMaxL3bV/view?usp=sharing | H74: =IF(C74="", "", IFERROR(VLOOKUP(C74, 'Tabla 2'!$A$2:$D$298, 2, FALSE), "")) -> Negocio Nacional | I74: =IF(C74="", "", IFERROR(VLOOKUP(C74, 'Tabla 2'!$A$2:$D$298, 3, FALSE), "")) -> 1 | J74: =IF(C74="", "", IFERROR(VLOOKUP(C74, 'Tabla 2'!$A$2:$D$298, 4, FALSE), "")) -> 1200000 | K74: Positivo | L74: TRUE | M74: Institucional | N74: Generalidades | O74: Guillermo Petracci | P74: 1
A75: 46149 | B75: Día de la industria minera: el rol estratégico de los proveedores para potenciar el crecimiento del sector | C75: Polígono Industrial | D75: Proactiva | E75: Orgánica | F75: Destaca la importancia de los proveedores locales para el crecimiento del sector minero. | G75: https://poligono.com.ar/2026/05/07/dia-de-la-industria-minera-el-rol-estrategico-de-los-proveedores-para-potenciar-el-crecimiento-del-sector/ | H75: =IF(C75="", "", IFERROR(VLOOKUP(C75, 'Tabla 2'!$A$2:$D$298, 2, FALSE), "")) -> Local BB | I75: =IF(C75="", "", IFERROR(VLOOKUP(C75, 'Tabla 2'!$A$2:$D$298, 3, FALSE), "")) -> 3 | J75: =IF(C75="", "", IFERROR(VLOOKUP(C75, 'Tabla 2'!$A$2:$D$298, 4, FALSE), "")) -> 0 | K75: Positivo | L75: TRUE | M75: Proveedor Estratégico | N75: Cadena de Valor y Sectores | O75: No menciona | P75: 1
A76: 46150 | B76: Litio: el rol clave de los proveedores en la nueva escala minera | C76: El Observador | D76: Proactiva | E76: Orgánica | F76: Informe sobre la cadena de valor del litio y el papel fundamental de los proveedores. | G76: https://www.elobservador.com.uy/argentina/economia-y-negocios/litio-el-rol-clave-los-proveedores-la-nueva-escala-minera-n6043646 | H76: Negocio Nacional | I76: =IF(C76="", "", IFERROR(VLOOKUP(C76, 'Tabla 2'!$A$2:$D$298, 3, FALSE), "")) -> 1 | J76: =IF(C76="", "", IFERROR(VLOOKUP(C76, 'Tabla 2'!$A$2:$D$298, 4, FALSE), "")) -> 500000 | K76: Positivo | L76: TRUE | M76: Proveedor Estratégico | N76: Cadena de Valor y Sectores | O76: No menciona | P76: 1
A77: 46152 | B77: Posta para inflamables Puerto Bahía Blanca | C77: GlobalPorts | D77: Espontánea | E77: Orgánica | F77: Reporte sobre la infraestructura y operaciones de la posta de inflamables en Bahía Blanca. | G77: https://www.globalports.com.ar/posta-para-inflamables-puerto-bahia-blanca/ | H77: =IF(C77="", "", IFERROR(VLOOKUP(C77, 'Tabla 2'!$A$2:$D$298, 2, FALSE), "")) -> Generalista Nacional | I77: =IF(C77="", "", IFERROR(VLOOKUP(C77, 'Tabla 2'!$A$2:$D$298, 3, FALSE), "")) -> 3 | J77: =IF(C77="", "", IFERROR(VLOOKUP(C77, 'Tabla 2'!$A$2:$D$298, 4, FALSE), "")) -> 0 | K77: Positivo | L77: TRUE | M77: Proveedor Estratégico | N77: Logística y Seguridad | O77: No menciona | P77: 1
A78: 46157 | B78: Competitividad y valor agregado: temas de la Jornada Petroquímica 2026 del IPA | C78: EconoJournal | D78: Espontánea | E78: Orgánica | F78: Anticipo de los ejes temáticos de la Jornada Petroquímica 2026 organizada por el IPA. | G78: https://econojournal.com.ar/2026/05/competitividad-y-valor-agregado-los-temas-que-marcaran-la-agenda-de-la-jornada-petroquimica-2026-del-ipa/ | H78: =IF(C78="", "", IFERROR(VLOOKUP(C78, 'Tabla 2'!$A$2:$D$298, 2, FALSE), "")) -> Negocio Nacional | I78: =IF(C78="", "", IFERROR(VLOOKUP(C78, 'Tabla 2'!$A$2:$D$298, 3, FALSE), "")) -> 1 | J78: =IF(C78="", "", IFERROR(VLOOKUP(C78, 'Tabla 2'!$A$2:$D$298, 4, FALSE), "")) -> 1800000 | K78: Positivo | L78: TRUE | M78: Institucional | N78: Escenario Político Económico | O78: Guillermo Petracci | P78: 1
A79: 46162 | B79: Escuelas técnicas bajo fuego: las quieren desfinanciadas | C79: La Izquierda Diario | D79: Espontánea | E79: Orgánica | F79: Análisis crítico sobre las reformas en educación técnica y su impacto en el financiamiento. | G79: https://www.laizquierdadiario.com/Escuelas-tecnicas-bajo-fuego-las-quieren-desfinanciadas-descentralizadas-y-para-las-empresas | H79: =IF(C79="", "", IFERROR(VLOOKUP(C79, 'Tabla 2'!$A$2:$D$298, 2, FALSE), "")) -> Generalista Nacional | I79: =IF(C79="", "", IFERROR(VLOOKUP(C79, 'Tabla 2'!$A$2:$D$298, 3, FALSE), "")) -> 3 | J79: =IF(C79="", "", IFERROR(VLOOKUP(C79, 'Tabla 2'!$A$2:$D$298, 4, FALSE), "")) -> 0 | K79: Positivo | M79: Sustentabilidad | N79: Relaciones con la Comunidad | O79: No menciona | P79: 1
A80: 46162 | B80: Competitividad y valor agregado: temas de la Jornada Petroquímica 2026 del IPA | C80: Diario El Paso | D80: Espontánea | E80: Orgánica | F80: Detalles sobre la agenda y objetivos estratégicos del próximo encuentro del sector. | G80: https://www.diarioelpaso.com/2026/05/20/competitividad-y-valor-agregado-los-temas-que-marcaran-la-agenda-de-la-jornada-petroquimica-2026-del-ipa/ | H80: =IF(C80="", "", IFERROR(VLOOKUP(C80, 'Tabla 2'!$A$2:$D$298, 2, FALSE), "")) -> Generalista Nacional | I80: =IF(C80="", "", IFERROR(VLOOKUP(C80, 'Tabla 2'!$A$2:$D$298, 3, FALSE), "")) -> 3 | J80: =IF(C80="", "", IFERROR(VLOOKUP(C80, 'Tabla 2'!$A$2:$D$298, 4, FALSE), "")) -> 0 | K80: Positivo | L80: TRUE | M80: Institucional | N80: Escenario Político Económico | O80: Guillermo Petracci | P80: 1
A81: 46163 | B81: Competitividad y valor agregado: temas de la Jornada Petroquímica 2026 del IPA | C81: InfoCámaras | D81: Espontánea | E81: Orgánica | F81: Resumen de la propuesta temática para el evento anual del Instituto Petroquímico Argentino. | G81: https://www.infocamaras.com.ar/competitividad-y-valor-agregado-los-temas-que-marcaran-la-agenda-de-la-jornada-petroquimica-2026-del-ipa/ | H81: =IF(C81="", "", IFERROR(VLOOKUP(C81, 'Tabla 2'!$A$2:$D$298, 2, FALSE), "")) -> Generalista Nacional | I81: =IF(C81="", "", IFERROR(VLOOKUP(C81, 'Tabla 2'!$A$2:$D$298, 3, FALSE), "")) -> 3 | J81: =IF(C81="", "", IFERROR(VLOOKUP(C81, 'Tabla 2'!$A$2:$D$298, 4, FALSE), "")) -> 0 | K81: Positivo | L81: TRUE | M81: Institucional | N81: Escenario Político Económico | O81: Guillermo Petracci | P81: 1
A82: 46163 | B82: Competitividad y valor agregado: temas de la Jornada Petroquímica 2026 del IPA | C82: Norte en Línea | D82: Espontánea | E82: Orgánica | F82: Información sobre la Jornada Petroquímica enfocada en la competitividad industrial. | G82: https://norteenlinea.com/competitividad-y-valor-agregado-los-temas-que-marcaran-la-agenda-de-la-jornada-petroquimica-2026-del-ipa/ | H82: =IF(C82="", "", IFERROR(VLOOKUP(C82, 'Tabla 2'!$A$2:$D$298, 2, FALSE), "")) -> Generalista Nacional | I82: =IF(C82="", "", IFERROR(VLOOKUP(C82, 'Tabla 2'!$A$2:$D$298, 3, FALSE), "")) -> 3 | J82: =IF(C82="", "", IFERROR(VLOOKUP(C82, 'Tabla 2'!$A$2:$D$298, 4, FALSE), "")) -> 0 | K82: Positivo | L82: TRUE | M82: Institucional | N82: Escenario Político Económico | O82: Guillermo Petracci | P82: 1
A83: 46164 | B83: El IPA hará el 9 de junio la Jornada Petroquímica 2026 en el C3 | C83: Mercado | D83: Espontánea | E83: Orgánica | F83: Anuncio oficial de la fecha y sede (Centro Cultural de la Ciencia) del evento del IPA. | G83: https://mercado.com.ar/agenda/el-ipa-hara-el-9-de-junio-la-jornada-petroquimica-2026-en-el-c3 | H83: =IF(C83="", "", IFERROR(VLOOKUP(C83, 'Tabla 2'!$A$2:$D$298, 2, FALSE), "")) -> Negocio Nacional | I83: =IF(C83="", "", IFERROR(VLOOKUP(C83, 'Tabla 2'!$A$2:$D$298, 3, FALSE), "")) -> 1 | J83: =IF(C83="", "", IFERROR(VLOOKUP(C83, 'Tabla 2'!$A$2:$D$298, 4, FALSE), "")) -> 500000 | K83: Positivo | M83: Institucional | N83: Generalidades | O83: Guillermo Petracci | P83: 1
A84: 46164 | B84: Unipar ratificó su apoyo a Huertas de la Ciudad y ya impulsa 70 huertas en Bahía Blanca | C84: Argen Ports web | D84: Proactiva | E84: Orgánica | F84: Unipar renovó su compromiso con el programa Huertas de la Ciudad | G84: https://argenports.com/nota/unipar-ratifico-su-apoyo-a-huertas-de-la-ciudad-y-ya-impulsa-70-huertas-en-bahia-blanca/ | H84: =IF(C84="", "", IFERROR(VLOOKUP(C84, 'Tabla 2'!$A$2:$D$298, 2, FALSE), "")) -> Local BB | I84: =IF(C84="", "", IFERROR(VLOOKUP(C84, 'Tabla 2'!$A$2:$D$298, 3, FALSE), "")) -> 2 | J84: =IF(C84="", "", IFERROR(VLOOKUP(C84, 'Tabla 2'!$A$2:$D$298, 4, FALSE), "")) -> 0 | K84: Positivo | L84: TRUE | M84: Sustentabilidad | N84: Relaciones con la Comunidad | O84: No menciona | P84: 1
A85: 46164 | B85: Cuarto año de Huertas de la Ciudad junto a Unipar | C85: Frente a Cano | D85: Proactiva | E85: Orgánica | F85: Celebración del cuarto año de colaboración entre Unipar y el programa municipal de huertas comunitarias en Bahía Blanca. | G85: https://frenteacano.com.ar/cuarto-ano-de-huertas-de-la-ciudad-junto-a-unipar/ | H85: =IF(C85="", "", IFERROR(VLOOKUP(C85, 'Tabla 2'!$A$2:$D$298, 2, FALSE), "")) -> Local BB | I85: =IF(C85="", "", IFERROR(VLOOKUP(C85, 'Tabla 2'!$A$2:$D$298, 3, FALSE), "")) -> 1 | J85: =IF(C85="", "", IFERROR(VLOOKUP(C85, 'Tabla 2'!$A$2:$D$298, 4, FALSE), "")) -> 800000 | K85: Positivo | L85: TRUE | M85: Sustentabilidad | N85: Relaciones con la Comunidad | O85: No menciona | P85: 1
A86: 46164 | B86: Unipar acompaña por cuarto año a Huertas de la Ciudad | C86: Ingeniero White | D86: Proactiva | E86: Orgánica | F86: La empresa Unipar mantiene su apoyo sostenido al proyecto de huertas urbanas locales por cuarto año consecutivo. | G86: https://www.ingenierowhite.com/2026/05/22/unipar-acompana-por-cuarto-ano-a-huertas-de-la-ciudad/ | H86: =IF(C86="", "", IFERROR(VLOOKUP(C86, 'Tabla 2'!$A$2:$D$298, 2, FALSE), "")) -> Local BB | I86: =IF(C86="", "", IFERROR(VLOOKUP(C86, 'Tabla 2'!$A$2:$D$298, 3, FALSE), "")) -> 1 | J86: =IF(C86="", "", IFERROR(VLOOKUP(C86, 'Tabla 2'!$A$2:$D$298, 4, FALSE), "")) -> 500000 | K86: Positivo | L86: TRUE | M86: Sustentabilidad | N86: Relaciones con la Comunidad | O86: No menciona | P86: 1
A87: 46164 | B87: Unipar acompaña por cuarto año a Huertas de la Ciudad | C87: Polígono Industrial | D87: Proactiva | E87: Orgánica | F87: Informe sobre la continuidad de la alianza estratégica entre Unipar y la iniciativa de huertas bahienses. | G87: https://poligono.com.ar/2026/05/22/unipar-acompana-por-cuarto-ano-a-huertas-de-la-ciudad/ | H87: =IF(C87="", "", IFERROR(VLOOKUP(C87, 'Tabla 2'!$A$2:$D$298, 2, FALSE), "")) -> Local BB | I87: =IF(C87="", "", IFERROR(VLOOKUP(C87, 'Tabla 2'!$A$2:$D$298, 3, FALSE), "")) -> 3 | J87: =IF(C87="", "", IFERROR(VLOOKUP(C87, 'Tabla 2'!$A$2:$D$298, 4, FALSE), "")) -> 0 | K87: Positivo | L87: TRUE | M87: Sustentabilidad | N87: Relaciones con la Comunidad | O87: No menciona | P87: 1
A88: 46169 | B88: Del shale al valor agregado: la industria petroquímica busca convertir el boom de Vaca Muerta en inversiones | C88: Mejor Energía | D88: Espontánea | E88: Orgánica | F88: Análisis sobre cómo la industria petroquímica busca capitalizar el recurso de Vaca Muerta mediante nuevas inversiones y agregado de valor. | G88: https://www.mejorenergia.com.ar/noticias/2026/05/27/5709-del-shale-al-valor-agregado-la-industria-petroquimica-busca-convertir-el-boom-de-vaca-muerta-en-inversiones | H88: =IF(C88="", "", IFERROR(VLOOKUP(C88, 'Tabla 2'!$A$2:$D$298, 2, FALSE), "")) -> Negocio Nacional | I88: =IF(C88="", "", IFERROR(VLOOKUP(C88, 'Tabla 2'!$A$2:$D$298, 3, FALSE), "")) -> 2 | J88: =IF(C88="", "", IFERROR(VLOOKUP(C88, 'Tabla 2'!$A$2:$D$298, 4, FALSE), "")) -> 0 | K88: Positivo | M88: Proveedor Estratégico | N88: Cadena de Valor y Sectores | O88: No menciona | P88: 1
A89: 46169 | B89: El IPA realizará la Jornada Petroquímica 2026 el 9 de junio en el C3 | C89: Prensa Energética | D89: Espontánea | E89: Orgánica | F89: Difusión de la convocatoria del Instituto Petroquímico Argentino para su evento anual centrado en la competitividad del sector. | G89: https://www.prensa-energetica.com.ar/Prensa-Energetica-Nota-689.html | H89: =IF(C89="", "", IFERROR(VLOOKUP(C89, 'Tabla 2'!$A$2:$D$298, 2, FALSE), "")) -> Generalista Nacional | I89: =IF(C89="", "", IFERROR(VLOOKUP(C89, 'Tabla 2'!$A$2:$D$298, 3, FALSE), "")) -> 3 | J89: =IF(C89="", "", IFERROR(VLOOKUP(C89, 'Tabla 2'!$A$2:$D$298, 4, FALSE), "")) -> 0 | K89: Positivo | L89: TRUE | M89: Institucional | N89: Escenario Político Económico | O89: Guillermo Petracci | P89: 1
A90: 46169 | B90: El IPA realizará la Jornada Petroquímica 2026 el 9 de junio en el C3 | C90: RunRun Energético | D90: Espontánea | E90: Orgánica | F90: Anuncio sobre la realización de la jornada técnica del IPA en el Centro Cultural de la Ciencia (C3) para debatir el futuro de la industria. | G90: https://runrunenergetico.com/el-ipa-realizara-la-jornada-petroquimica-2026-el-9-de-junio-en-el-c3/ | H90: =IF(C90="", "", IFERROR(VLOOKUP(C90, 'Tabla 2'!$A$2:$D$298, 2, FALSE), "")) -> Negocio Nacional | I90: =IF(C90="", "", IFERROR(VLOOKUP(C90, 'Tabla 2'!$A$2:$D$298, 3, FALSE), "")) -> 2 | J90: =IF(C90="", "", IFERROR(VLOOKUP(C90, 'Tabla 2'!$A$2:$D$298, 4, FALSE), "")) -> 0 | K90: Positivo | L90: TRUE | M90: Institucional | N90: Escenario Político Económico | O90: Guillermo Petracci | P90: 1
A91: 46169 | B91: Competitividad y valor agregado: los temas que marcarán la agenda de la Jornada Petroquímica 2026 del IPA | C91: Cover News | D91: Espontánea | E91: Orgánica | F91: Resumen de los ejes temáticos de la próxima Jornada Petroquímica | G91: https://covernews.press/competitividad-y-valor-agregado-los-temas-que-marcaran-la-agenda-de-la-jornada-petroquimica-2026-del-ipa/ | H91: =IF(C91="", "", IFERROR(VLOOKUP(C91, 'Tabla 2'!$A$2:$D$298, 2, FALSE), "")) -> Generalista Nacional | I91: =IF(C91="", "", IFERROR(VLOOKUP(C91, 'Tabla 2'!$A$2:$D$298, 3, FALSE), "")) -> 3 | J91: =IF(C91="", "", IFERROR(VLOOKUP(C91, 'Tabla 2'!$A$2:$D$298, 4, FALSE), "")) -> 0 | K91: Positivo | L91: TRUE | M91: Institucional | N91: Escenario Político Económico | O91: Guillermo Petracci | P91: 1
A92: 46174 | B92: Unipar superó sus metas ambientales y destacó avances en Bahía Blanca en su reporte de sustentabilidad 2025 | C92: Argen Ports web | D92: Proactiva | E92: Orgánica | F92: Reporte sobre el cumplimiento de metas ambientales y avances en Bahía Blanca según el reporte de sustentabilidad 2025 de Unipar. | G92: https://argenports.com/nota/unipar-supero-sus-metas-ambientales-y-destaco-avances-en-bahia-blanca-en-su-reporte-de-sustentabilidad-2025/ | H92: =IF($C92="ArgenPorts", VLOOKUP("Argen Ports web", 'Tabla 2'!$A$1:$D$301, 2, FALSE), VLOOKUP($C92, 'Tabla 2'!$A$1:$D$301, 2, FALSE)) -> Local BB | I92: =IF($C92="ArgenPorts", VLOOKUP("Argen Ports web", 'Tabla 2'!$A$1:$D$301, 3, FALSE), VLOOKUP($C92, 'Tabla 2'!$A$1:$D$301, 3, FALSE)) -> 2 | J92: =IF($C92="ArgenPorts", VLOOKUP("Argen Ports web", 'Tabla 2'!$A$1:$D$301, 4, FALSE), VLOOKUP($C92, 'Tabla 2'!$A$1:$D$301, 4, FALSE)) -> 0 | K92: Positivo | L92: TRUE | M92: Sustentabilidad | N92: Estrategia ESG | O92: Rodrigo Cannaval | P92: 1
A93: 46174 | B93: Unipar presentó su reporte de sustentabilidad 2025 con avances récord en energía y emisiones | C93: Futuro Sustentable | D93: Proactiva | E93: Orgánica | F93: Cobertura sobre la presentación del reporte de sustentabilidad 2025 de Unipar, destacando avances récord en energía y emisiones. | G93: https://futurosustentable.com.ar/unipar-presento-su-reporte-de-sustentabilidad-2025-con-avances-record-en-energia-y-emisiones/ | H93: =IF(C93="", "", IFERROR(VLOOKUP(C93, 'Tabla 2'!$A$2:$D$298, 2, FALSE), "")) -> Sustentabilidad Nacional | I93: =IF(C93="", "", IFERROR(VLOOKUP(C93, 'Tabla 2'!$A$2:$D$298, 3, FALSE), "")) -> 2 | J93: =IF(C93="", "", IFERROR(VLOOKUP(C93, 'Tabla 2'!$A$2:$D$298, 4, FALSE), "")) -> 0 | K93: Positivo | L93: TRUE | M93: Sustentabilidad | N93: Estrategia ESG | O93: Rodrigo Cannaval | P93: 1
A94: 46174 | B94: Unipar presenta su reporte de sostenibilidad 2025 con resultados que superan el cumplimiento de sus compromisos | C94: La Nueva Provincia | D94: Proactiva | E94: Orgánica | F94: Noticia sobre los resultados del reporte de sostenibilidad 2025 de Unipar, superando sus compromisos. | G94: https://www.lanueva.com/nota/2026-6-1-16-37-0-unipar-presenta-su-reporte-de-sostenibilidad-2025-con-resultados-que-superan-el-cumplimiento-de-sus-compromisos#:~:text=La%20ciudad.-,Unipar%20presenta%20su%20Reporte%20de%20Sostenibilidad%202025%20con%20resultados%20que,seguridad%20y%20la%20evoluci%C3%B3n%20continua. | H94: =IF(C94="", "", IFERROR(VLOOKUP(C94, 'Tabla 2'!$A$2:$D$298, 2, FALSE), "")) -> Local BB | I94: =IF(C94="", "", IFERROR(VLOOKUP(C94, 'Tabla 2'!$A$2:$D$298, 3, FALSE), "")) -> 1 | J94: =IF(C94="", "", IFERROR(VLOOKUP(C94, 'Tabla 2'!$A$2:$D$298, 4, FALSE), "")) -> 900000 | K94: Positivo | L94: TRUE | M94: Sustentabilidad | N94: Estrategia ESG | O94: Rodrigo Cannaval | P94: 1
A95: 46174 | B95: Unipar presentó su reporte de sostenibilidad 2025 | C95: Polígono Industrial | D95: Proactiva | E95: Orgánica | F95: Información sobre la presentación del reporte de sostenibilidad 2025 de Unipar. | G95: https://poligono.com.ar/2026/06/01/unipar-presento-su-reporte-de-sostenibilidad-2025/ | H95: =IF(C95="", "", IFERROR(VLOOKUP(C95, 'Tabla 2'!$A$2:$D$298, 2, FALSE), "")) -> Local BB | I95: =IF(C95="", "", IFERROR(VLOOKUP(C95, 'Tabla 2'!$A$2:$D$298, 3, FALSE), "")) -> 3 | J95: =IF(C95="", "", IFERROR(VLOOKUP(C95, 'Tabla 2'!$A$2:$D$298, 4, FALSE), "")) -> 0 | K95: Positivo | L95: TRUE | M95: Sustentabilidad | N95: Estrategia ESG | O95: Rodrigo Cannaval | P95: 1
A96: 46174 | B96: Unipar presentó su reporte de sostenibilidad 2025 | C96: Ciudad Portuaria | D96: Proactiva | E96: Orgánica | F96: Información sobre la presentación del reporte de sostenibilidad 2025 de Unipar. | G96: https://ciudadportuaria.com.ar/actualidad/unipar-presento-su-reporte-de-sostenibilidad-2025/ | H96: =IF(C96="", "", IFERROR(VLOOKUP(C96, 'Tabla 2'!$A$2:$D$298, 2, FALSE), "")) -> Local BB | I96: =IF(C96="", "", IFERROR(VLOOKUP(C96, 'Tabla 2'!$A$2:$D$298, 3, FALSE), "")) -> 2 | J96: =IF(C96="", "", IFERROR(VLOOKUP(C96, 'Tabla 2'!$A$2:$D$298, 4, FALSE), "")) -> 0 | K96: Positivo | L96: TRUE | M96: Sustentabilidad | N96: Estrategia ESG | O96: Rodrigo Cannaval | P96: 1
A97: 46174 | B97: Competitividad, inversión y desarrollo industrial: ejes de la Jornada Petroquímica 2026 del IPA | C97: Impacto Local | D97: Proactiva | E97: Orgánica | F97: Artículo sobre los ejes de la Jornada Petroquímica 2026 del IPA, enfocados en competitividad, inversión y desarrollo industrial. | G97: https://impactolocal.com.ar/competitividad-inversion-y-desarrollo-industrial-ejes-de-la-jornada-petroquimica-2026-del-ipa | H97: Local BB | I97: 3 | J97: 500000 | K97: Positivo | L97: TRUE | M97: Institucional | N97: Escenario Político Económico | O97: Guillermo Petracci | P97: 1
A98: 46174 | B98: Competitividad, inversión y desarrollo industrial: ejes de la Jornada Petroquímica 2026 del IPA | C98: Norte en Línea | D98: Proactiva | E98: Orgánica | F98: Artículo sobre los ejes de la Jornada Petroquímica 2026 del IPA, enfocados en competitividad, inversión y desarrollo industrial. | G98: https://norteenlinea.com/competitividad-inversion-y-desarrollo-industrial-ejes-de-la-jornada-petroquimica-2026-del-ipa/ | H98: =IF(C98="", "", IFERROR(VLOOKUP(C98, 'Tabla 2'!$A$2:$D$298, 2, FALSE), "")) -> Generalista Nacional | I98: =IF(C98="", "", IFERROR(VLOOKUP(C98, 'Tabla 2'!$A$2:$D$298, 3, FALSE), "")) -> 3 | J98: =IF(C98="", "", IFERROR(VLOOKUP(C98, 'Tabla 2'!$A$2:$D$298, 4, FALSE), "")) -> 0 | K98: Positivo | L98: TRUE | M98: Institucional | N98: Escenario Político Económico | O98: Guillermo Petracci | P98: 1
A99: 46174 | B99: En Unipar la sustentabilidad no se gestiona como una agenda paralela | C99: Sustenomics | D99: Proactiva | E99: Orgánica | F99: Nota sobre la gestión integral de la sustentabilidad en Unipar, destacando que no es una agenda paralela. | G99: https://sustenomics.com/en-unipar-la-sustentabilidad-no-se-gestiona-como-una-agenda-paralela/ | H99: =IF(C99="", "", IFERROR(VLOOKUP(C99, 'Tabla 2'!$A$2:$D$298, 2, FALSE), "")) -> Sustentabilidad Nacional | I99: =IF(C99="", "", IFERROR(VLOOKUP(C99, 'Tabla 2'!$A$2:$D$298, 3, FALSE), "")) -> 1 | J99: =IF(C99="", "", IFERROR(VLOOKUP(C99, 'Tabla 2'!$A$2:$D$298, 4, FALSE), "")) -> 700000 | K99: Positivo | L99: TRUE | M99: Sustentabilidad | N99: Estrategia ESG | O99: Rodrigo Cannaval | P99: 1
A100: 46174 | B100: Competitividad, inversión y desarrollo industrial: ejes de la Jornada Petroquímica 2026 del IPA | C100: EconoJournal | D100: Espontánea | E100: =IF(OR(D100="Espontánea", D100="Reactiva"), "Orgánica", "") -> Orgánica | F100: Artículo sobre los ejes de la Jornada Petroquímica 2026 del IPA, enfocados en competitividad, inversión y desarrollo industrial. | G100: https://econojournal.com.ar/2026/06/competitividad-inversion-y-desarrollo-industrial-ejes-de-la-jornada-petroquimica-2026-del-ipa/ | H100: =IF(C100="", "", IFERROR(VLOOKUP(C100, 'Tabla 2'!$A$2:$D$298, 2, FALSE), "")) -> Negocio Nacional | I100: =IF(C100="", "", IFERROR(VLOOKUP(C100, 'Tabla 2'!$A$2:$D$298, 3, FALSE), "")) -> 1 | J100: =IF(C100="", "", IFERROR(VLOOKUP(C100, 'Tabla 2'!$A$2:$D$298, 4, FALSE), "")) -> 1800000 | K100: Positivo | L100: TRUE | M100: Institucional | N100: Escenario Político Económico | O100: Guillermo Petracci | P100: 1
...

Sheet Tabla 2
A1: LISTA DE MEDIOS (Base) | B1: Tipo de Medio (Base) | C1: Tier (Base) | D1: Valor Estimado (Base) | E1: Voceros (Base)
A2: Clarin | B2: Generalista Nacional | C2: 1 | D2: 6000000 | E2: Rodrigo Cannaval
A3: La Nación | B3: Generalista Nacional | C3: 1 | D3: 7000000 | E3: Guillermo Petracci
A4: El Cronista | B4: Negocio Nacional | C4: 1 | D4: 1200000 | E4: Laura Gutiérrez
A5: Ámbito Financiero | B5: Negocio Nacional | C5: 1 | D5: 1200000 | E5: Martín Fasano
A6: Apertura | B6: Negocio Nacional | C6: 1 | D6: 1200000 | E6: Alexandre Castro
A7: BAE Negocios | B7: Negocio Nacional | C7: 1 | D7: 800000 | E7: Matías Moreno
A8: Infobae | B8: Generalista Nacional | C8: 1 | D8: 6000000 | E8: Gabriel Stachiotti
A9: iProfesional | B9: Generalista Nacional | C9: 1 | D9: 800000 | E9: Cecilia Marinesco
A10: Mercado | B10: Negocio Nacional | C10: 1 | D10: 500000 | E10: Ignacio Garriz
A11: Revista Petroquímica | B11: Negocio Nacional | C11: 1 | D11: 500000 | E11: Rodrigo Capdevila
A12: TV Pública | B12: Generalista Nacional | C12: 1 | D12: 1800 | E12: Ezequiel Báez
A13: El Tribuno | B13: Generalista Nacional | C13: 1 | D13: 800000
A14: EconoJournal | B14: Negocio Nacional | C14: 1 | D14: 1800000
A15: El Economista | B15: Negocio Nacional | C15: 1 | D15: 800000
A16: La Opinión Austral | B16: Generalista Nacional | C16: 1 | D16: 800000
A17: Visión Sustentable | B17: Sustentabilidad Nacional | C17: 1 | D17: 600000
A18: Sustenomics | B18: Sustentabilidad Nacional | C18: 1 | D18: 700000
A19: Prensa Económica | B19: Generalista Nacional | C19: 1 | D19: 200000
A20: Forbes | B20: Negocio Nacional | C20: 1 | D20: 8000000
A21: Perfil | B21: Generalista Nacional | C21: 1 | D21: 1000000
A22: Diario Río Negro | B22: Generalista Nacional | C22: 1 | D22: 500000
A23: El Observador | B23: Negocios | C23: 1 | D23: 500000
A24: Canal 7 Bahia Blanca | B24: Local BB | C24: 1 | D24: 5000000
... A307: Semanario Bariloche | B307: Generalista Nacional | C307: 3 | D307: 0
A308: Inversor Latam | B308: Generalista Nacional | C308: 3 | D308: ARS0,00
A309: Bahía Política | B309: Local BB | C309: 3 | D309: ARS0,00
A310: Crónica del NOA | B310: Generalista Nacional | C310: 3 | D310: ARS0,00
A311: Revista Imagen | B311: Generalista Nacional | C311: 3 | D311: ARS0,00
A312: Nuevo Enfoque Urbano | B312: Generalista Nacional | C312: 3 | D312: 0
A313: BNAmericas | B313: Generalista Nacional | C313: 1 | D313: 1000000

Sheet Resumen Tier 1
A1: Mes | B1: Tier1
A2: 2026-ene | B2: 5
A3: 2026-feb | B3: 11
A4: 2026-mar | B4: 9
A5: 2026-abr | B5: 13
A6: 2026-may | B6: 5
A7: 2026-jun | B7: 18
A8: 46204 | B8: 7
A9: Total | B9: =SUM(B2:B8) -> 68
